{
  "#conformance": {
    "current": {
      "number": "5",
      "spec": "ISO Common Encryption Protection Scheme for ISO Base Media File Format Stream Format",
      "text": "Conformance",
      "url": "https://w3c.github.io/encrypted-media/format-registry/stream/mp4.html#conformance"
    }
  },
  "#detect-encrypted-blocks": {
    "current": {
      "number": "3",
      "spec": "ISO Common Encryption Protection Scheme for ISO Base Media File Format Stream Format",
      "text": "Detecting Encrypted Blocks",
      "url": "https://w3c.github.io/encrypted-media/format-registry/stream/mp4.html#detect-encrypted-blocks"
    }
  },
  "#detect-format": {
    "current": {
      "number": "2",
      "spec": "ISO Common Encryption Protection Scheme for ISO Base Media File Format Stream Format",
      "text": "Detection",
      "url": "https://w3c.github.io/encrypted-media/format-registry/stream/mp4.html#detect-format"
    }
  },
  "#init-data": {
    "current": {
      "number": "4",
      "spec": "ISO Common Encryption Protection Scheme for ISO Base Media File Format Stream Format",
      "text": "Initialization Data Extraction",
      "url": "https://w3c.github.io/encrypted-media/format-registry/stream/mp4.html#init-data"
    }
  },
  "#normative-references": {
    "current": {
      "number": "A.1",
      "spec": "ISO Common Encryption Protection Scheme for ISO Base Media File Format Stream Format",
      "text": "Normative references",
      "url": "https://w3c.github.io/encrypted-media/format-registry/stream/mp4.html#normative-references"
    }
  },
  "#references": {
    "current": {
      "number": "A",
      "spec": "ISO Common Encryption Protection Scheme for ISO Base Media File Format Stream Format",
      "text": "References",
      "url": "https://w3c.github.io/encrypted-media/format-registry/stream/mp4.html#references"
    }
  },
  "#stream-format": {
    "current": {
      "number": "1",
      "spec": "ISO Common Encryption Protection Scheme for ISO Base Media File Format Stream Format",
      "text": "Stream Format",
      "url": "https://w3c.github.io/encrypted-media/format-registry/stream/mp4.html#stream-format"
    }
  },
  "#title": {
    "current": {
      "number": "",
      "spec": "ISO Common Encryption Protection Scheme for ISO Base Media File Format Stream Format",
      "text": "ISO Common Encryption Protection Scheme for ISO Base Media File Format Stream Format",
      "url": "https://w3c.github.io/encrypted-media/format-registry/stream/mp4.html#title"
    }
  },
  "#toc": {
    "current": {
      "number": "",
      "spec": "ISO Common Encryption Protection Scheme for ISO Base Media File Format Stream Format",
      "text": "Table of Contents",
      "url": "https://w3c.github.io/encrypted-media/format-registry/stream/mp4.html#toc"
    }
  }
}