{
  "#acceptable-use": {
    "current": {
      "number": "9.9",
      "spec": "Verifiable Credentials Data Model v2.0",
      "text": "Acceptable Use",
      "url": "https://w3c.github.io/vc-data-model/#acceptable-use"
    },
    "snapshot": {
      "number": "9.9",
      "spec": "Verifiable Credentials Data Model v2.0",
      "text": "Acceptable Use",
      "url": "https://www.w3.org/TR/vc-data-model-2.0/#acceptable-use"
    }
  },
  "#accessibility-considerations": {
    "current": {
      "number": "",
      "spec": "Verifiable Credentials Data Model v2.0",
      "text": "10. Accessibility Considerations",
      "url": "https://w3c.github.io/vc-data-model/#accessibility-considerations"
    },
    "snapshot": {
      "number": "",
      "spec": "Verifiable Credentials Data Model v2.0",
      "text": "10. Accessibility Considerations",
      "url": "https://www.w3.org/TR/vc-data-model-2.0/#accessibility-considerations"
    }
  },
  "#acknowledgements": {
    "current": {
      "number": "F",
      "spec": "Verifiable Credentials Data Model v2.0",
      "text": "Acknowledgements",
      "url": "https://w3c.github.io/vc-data-model/#acknowledgements"
    },
    "snapshot": {
      "number": "F",
      "spec": "Verifiable Credentials Data Model v2.0",
      "text": "Acknowledgements",
      "url": "https://www.w3.org/TR/vc-data-model-2.0/#acknowledgements"
    }
  },
  "#additional-diagrams-for-verifiable-presentations": {
    "current": {
      "number": "D",
      "spec": "Verifiable Credentials Data Model v2.0",
      "text": "Additional Diagrams for Verifiable Presentations",
      "url": "https://w3c.github.io/vc-data-model/#additional-diagrams-for-verifiable-presentations"
    },
    "snapshot": {
      "number": "D",
      "spec": "Verifiable Credentials Data Model v2.0",
      "text": "Additional Diagrams for Verifiable Presentations",
      "url": "https://www.w3.org/TR/vc-data-model-2.0/#additional-diagrams-for-verifiable-presentations"
    }
  },
  "#advanced-concepts": {
    "current": {
      "number": "5",
      "spec": "Verifiable Credentials Data Model v2.0",
      "text": "Advanced Concepts",
      "url": "https://w3c.github.io/vc-data-model/#advanced-concepts"
    },
    "snapshot": {
      "number": "5",
      "spec": "Verifiable Credentials Data Model v2.0",
      "text": "Advanced Concepts",
      "url": "https://www.w3.org/TR/vc-data-model-2.0/#advanced-concepts"
    }
  },
  "#aggregation-of-credentials": {
    "current": {
      "number": "8.13",
      "spec": "Verifiable Credentials Data Model v2.0",
      "text": "Aggregation of Credentials",
      "url": "https://w3c.github.io/vc-data-model/#aggregation-of-credentials"
    },
    "snapshot": {
      "number": "8.13",
      "spec": "Verifiable Credentials Data Model v2.0",
      "text": "Aggregation of Credentials",
      "url": "https://www.w3.org/TR/vc-data-model-2.0/#aggregation-of-credentials"
    }
  },
  "#algorithms": {
    "current": {
      "number": "7",
      "spec": "Verifiable Credentials Data Model v2.0",
      "text": "Algorithms",
      "url": "https://w3c.github.io/vc-data-model/#algorithms"
    },
    "snapshot": {
      "number": "7",
      "spec": "Verifiable Credentials Data Model v2.0",
      "text": "Algorithms",
      "url": "https://www.w3.org/TR/vc-data-model-2.0/#algorithms"
    }
  },
  "#artificial-intelligence-and-machine-learning": {
    "current": {
      "number": "A.11",
      "spec": "Verifiable Credentials Data Model v2.0",
      "text": "\"Artificial Intelligence\" and \"Machine Learning\"",
      "url": "https://w3c.github.io/vc-data-model/#artificial-intelligence-and-machine-learning"
    },
    "snapshot": {
      "number": "A.11",
      "spec": "Verifiable Credentials Data Model v2.0",
      "text": "\"Artificial Intelligence\" and \"Machine Learning\"",
      "url": "https://www.w3.org/TR/vc-data-model-2.0/#artificial-intelligence-and-machine-learning"
    }
  },
  "#authorization": {
    "current": {
      "number": "5.9",
      "spec": "Verifiable Credentials Data Model v2.0",
      "text": "Authorization",
      "url": "https://w3c.github.io/vc-data-model/#authorization"
    },
    "snapshot": {
      "number": "5.9",
      "spec": "Verifiable Credentials Data Model v2.0",
      "text": "Authorization",
      "url": "https://www.w3.org/TR/vc-data-model-2.0/#authorization"
    }
  },
  "#base-context": {
    "current": {
      "number": "B.1",
      "spec": "Verifiable Credentials Data Model v2.0",
      "text": "Base Context",
      "url": "https://w3c.github.io/vc-data-model/#base-context"
    },
    "snapshot": {
      "number": "B.1",
      "spec": "Verifiable Credentials Data Model v2.0",
      "text": "Base Context",
      "url": "https://www.w3.org/TR/vc-data-model-2.0/#base-context"
    }
  },
  "#basic-concepts": {
    "current": {
      "number": "4",
      "spec": "Verifiable Credentials Data Model v2.0",
      "text": "Basic Concepts",
      "url": "https://w3c.github.io/vc-data-model/#basic-concepts"
    },
    "snapshot": {
      "number": "4",
      "spec": "Verifiable Credentials Data Model v2.0",
      "text": "Basic Concepts",
      "url": "https://www.w3.org/TR/vc-data-model-2.0/#basic-concepts"
    }
  },
  "#bearer-credentials": {
    "current": {
      "number": "8.10",
      "spec": "Verifiable Credentials Data Model v2.0",
      "text": "Bearer Credentials",
      "url": "https://w3c.github.io/vc-data-model/#bearer-credentials"
    },
    "snapshot": {
      "number": "8.10",
      "spec": "Verifiable Credentials Data Model v2.0",
      "text": "Bearer Credentials",
      "url": "https://www.w3.org/TR/vc-data-model-2.0/#bearer-credentials"
    }
  },
  "#bundling-dependent-claims": {
    "current": {
      "number": "9.6",
      "spec": "Verifiable Credentials Data Model v2.0",
      "text": "Bundling Dependent Claims",
      "url": "https://w3c.github.io/vc-data-model/#bundling-dependent-claims"
    },
    "snapshot": {
      "number": "9.6",
      "spec": "Verifiable Credentials Data Model v2.0",
      "text": "Bundling Dependent Claims",
      "url": "https://www.w3.org/TR/vc-data-model-2.0/#bundling-dependent-claims"
    }
  },
  "#claims": {
    "current": {
      "number": "3.1",
      "spec": "Verifiable Credentials Data Model v2.0",
      "text": "Claims",
      "url": "https://w3c.github.io/vc-data-model/#claims"
    },
    "snapshot": {
      "number": "3.1",
      "spec": "Verifiable Credentials Data Model v2.0",
      "text": "Claims",
      "url": "https://www.w3.org/TR/vc-data-model-2.0/#claims"
    }
  },
  "#code-injection": {
    "current": {
      "number": "9.10",
      "spec": "Verifiable Credentials Data Model v2.0",
      "text": "Code Injection",
      "url": "https://w3c.github.io/vc-data-model/#code-injection"
    },
    "snapshot": {
      "number": "9.10",
      "spec": "Verifiable Credentials Data Model v2.0",
      "text": "Code Injection",
      "url": "https://www.w3.org/TR/vc-data-model-2.0/#code-injection"
    }
  },
  "#conformance": {
    "current": {
      "number": "1.3",
      "spec": "Verifiable Credentials Data Model v2.0",
      "text": "Conformance",
      "url": "https://w3c.github.io/vc-data-model/#conformance"
    },
    "snapshot": {
      "number": "1.3",
      "spec": "Verifiable Credentials Data Model v2.0",
      "text": "Conformance",
      "url": "https://www.w3.org/TR/vc-data-model-2.0/#conformance"
    }
  },
  "#content-integrity-protection": {
    "current": {
      "number": "9.3",
      "spec": "Verifiable Credentials Data Model v2.0",
      "text": "Content Integrity Protection",
      "url": "https://w3c.github.io/vc-data-model/#content-integrity-protection"
    },
    "snapshot": {
      "number": "9.3",
      "spec": "Verifiable Credentials Data Model v2.0",
      "text": "Content Integrity Protection",
      "url": "https://www.w3.org/TR/vc-data-model-2.0/#content-integrity-protection"
    }
  },
  "#contexts": {
    "current": {
      "number": "4.3",
      "spec": "Verifiable Credentials Data Model v2.0",
      "text": "Contexts",
      "url": "https://w3c.github.io/vc-data-model/#contexts"
    },
    "snapshot": {
      "number": "4.3",
      "spec": "Verifiable Credentials Data Model v2.0",
      "text": "Contexts",
      "url": "https://www.w3.org/TR/vc-data-model-2.0/#contexts"
    }
  },
  "#contexts-vocabularies-types-and-credential-schemas": {
    "current": {
      "number": "B",
      "spec": "Verifiable Credentials Data Model v2.0",
      "text": "Contexts, Vocabularies, Types, and Credential Schemas",
      "url": "https://w3c.github.io/vc-data-model/#contexts-vocabularies-types-and-credential-schemas"
    },
    "snapshot": {
      "number": "B",
      "spec": "Verifiable Credentials Data Model v2.0",
      "text": "Contexts, Vocabularies, Types, and Credential Schemas",
      "url": "https://www.w3.org/TR/vc-data-model-2.0/#contexts-vocabularies-types-and-credential-schemas"
    }
  },
  "#core-data-model": {
    "current": {
      "number": "3",
      "spec": "Verifiable Credentials Data Model v2.0",
      "text": "Core Data Model",
      "url": "https://w3c.github.io/vc-data-model/#core-data-model"
    },
    "snapshot": {
      "number": "3",
      "spec": "Verifiable Credentials Data Model v2.0",
      "text": "Core Data Model",
      "url": "https://www.w3.org/TR/vc-data-model-2.0/#core-data-model"
    }
  },
  "#correlation-during-validation": {
    "current": {
      "number": "8.11",
      "spec": "Verifiable Credentials Data Model v2.0",
      "text": "Correlation During Validation",
      "url": "https://w3c.github.io/vc-data-model/#correlation-during-validation"
    },
    "snapshot": {
      "number": "8.11",
      "spec": "Verifiable Credentials Data Model v2.0",
      "text": "Correlation During Validation",
      "url": "https://www.w3.org/TR/vc-data-model-2.0/#correlation-during-validation"
    }
  },
  "#credential-subject": {
    "current": {
      "number": "4.8",
      "spec": "Verifiable Credentials Data Model v2.0",
      "text": "Credential Subject",
      "url": "https://w3c.github.io/vc-data-model/#credential-subject"
    },
    "snapshot": {
      "number": "4.8",
      "spec": "Verifiable Credentials Data Model v2.0",
      "text": "Credential Subject",
      "url": "https://www.w3.org/TR/vc-data-model-2.0/#credential-subject"
    }
  },
  "#credential-subject-0": {
    "current": {
      "number": "A.2",
      "spec": "Verifiable Credentials Data Model v2.0",
      "text": "Credential Subject",
      "url": "https://w3c.github.io/vc-data-model/#credential-subject-0"
    },
    "snapshot": {
      "number": "A.2",
      "spec": "Verifiable Credentials Data Model v2.0",
      "text": "Credential Subject",
      "url": "https://www.w3.org/TR/vc-data-model-2.0/#credential-subject-0"
    }
  },
  "#credential-type": {
    "current": {
      "number": "A.1",
      "spec": "Verifiable Credentials Data Model v2.0",
      "text": "Credential Type",
      "url": "https://w3c.github.io/vc-data-model/#credential-type"
    },
    "snapshot": {
      "number": "A.1",
      "spec": "Verifiable Credentials Data Model v2.0",
      "text": "Credential Type",
      "url": "https://www.w3.org/TR/vc-data-model-2.0/#credential-type"
    }
  },
  "#credentials": {
    "current": {
      "number": "3.2",
      "spec": "Verifiable Credentials Data Model v2.0",
      "text": "Credentials",
      "url": "https://w3c.github.io/vc-data-model/#credentials"
    },
    "snapshot": {
      "number": "3.2",
      "spec": "Verifiable Credentials Data Model v2.0",
      "text": "Credentials",
      "url": "https://www.w3.org/TR/vc-data-model-2.0/#credentials"
    }
  },
  "#cryptography-suites-and-libraries": {
    "current": {
      "number": "9.1",
      "spec": "Verifiable Credentials Data Model v2.0",
      "text": "Cryptography Suites and Libraries",
      "url": "https://w3c.github.io/vc-data-model/#cryptography-suites-and-libraries"
    },
    "snapshot": {
      "number": "9.1",
      "spec": "Verifiable Credentials Data Model v2.0",
      "text": "Cryptography Suites and Libraries",
      "url": "https://www.w3.org/TR/vc-data-model-2.0/#cryptography-suites-and-libraries"
    }
  },
  "#data-first-approaches": {
    "current": {
      "number": "10.1",
      "spec": "Verifiable Credentials Data Model v2.0",
      "text": "Data First Approaches",
      "url": "https://w3c.github.io/vc-data-model/#data-first-approaches"
    },
    "snapshot": {
      "number": "10.1",
      "spec": "Verifiable Credentials Data Model v2.0",
      "text": "Data First Approaches",
      "url": "https://www.w3.org/TR/vc-data-model-2.0/#data-first-approaches"
    }
  },
  "#data-schemas": {
    "current": {
      "number": "4.11",
      "spec": "Verifiable Credentials Data Model v2.0",
      "text": "Data Schemas",
      "url": "https://w3c.github.io/vc-data-model/#data-schemas"
    },
    "snapshot": {
      "number": "4.11",
      "spec": "Verifiable Credentials Data Model v2.0",
      "text": "Data Schemas",
      "url": "https://www.w3.org/TR/vc-data-model-2.0/#data-schemas"
    }
  },
  "#data-theft": {
    "current": {
      "number": "8.17",
      "spec": "Verifiable Credentials Data Model v2.0",
      "text": "Data Theft",
      "url": "https://w3c.github.io/vc-data-model/#data-theft"
    },
    "snapshot": {
      "number": "8.17",
      "spec": "Verifiable Credentials Data Model v2.0",
      "text": "Data Theft",
      "url": "https://www.w3.org/TR/vc-data-model-2.0/#data-theft"
    }
  },
  "#datatypes": {
    "current": {
      "number": "B.3",
      "spec": "Verifiable Credentials Data Model v2.0",
      "text": "Datatypes",
      "url": "https://w3c.github.io/vc-data-model/#datatypes"
    },
    "snapshot": {
      "number": "B.3",
      "spec": "Verifiable Credentials Data Model v2.0",
      "text": "Datatypes",
      "url": "https://www.w3.org/TR/vc-data-model-2.0/#datatypes"
    }
  },
  "#device-theft-and-impersonation": {
    "current": {
      "number": "9.8",
      "spec": "Verifiable Credentials Data Model v2.0",
      "text": "Device Theft and Impersonation",
      "url": "https://w3c.github.io/vc-data-model/#device-theft-and-impersonation"
    },
    "snapshot": {
      "number": "9.8",
      "spec": "Verifiable Credentials Data Model v2.0",
      "text": "Device Theft and Impersonation",
      "url": "https://www.w3.org/TR/vc-data-model-2.0/#device-theft-and-impersonation"
    }
  },
  "#device-tracking-and-fingerprinting": {
    "current": {
      "number": "8.7",
      "spec": "Verifiable Credentials Data Model v2.0",
      "text": "Device Tracking and Fingerprinting",
      "url": "https://w3c.github.io/vc-data-model/#device-tracking-and-fingerprinting"
    },
    "snapshot": {
      "number": "8.7",
      "spec": "Verifiable Credentials Data Model v2.0",
      "text": "Device Tracking and Fingerprinting",
      "url": "https://www.w3.org/TR/vc-data-model-2.0/#device-tracking-and-fingerprinting"
    }
  },
  "#differences-between-contexts-types-and-credentialschemas": {
    "current": {
      "number": "B.4",
      "spec": "Verifiable Credentials Data Model v2.0",
      "text": "Differences between Contexts, Types, and CredentialSchemas",
      "url": "https://w3c.github.io/vc-data-model/#differences-between-contexts-types-and-credentialschemas"
    },
    "snapshot": {
      "number": "B.4",
      "spec": "Verifiable Credentials Data Model v2.0",
      "text": "Differences between Contexts, Types, and CredentialSchemas",
      "url": "https://www.w3.org/TR/vc-data-model-2.0/#differences-between-contexts-types-and-credentialschemas"
    }
  },
  "#ecosystem-compatibility": {
    "current": {
      "number": "5.11",
      "spec": "Verifiable Credentials Data Model v2.0",
      "text": "Ecosystem Compatibility",
      "url": "https://w3c.github.io/vc-data-model/#ecosystem-compatibility"
    },
    "snapshot": {
      "number": "5.11",
      "spec": "Verifiable Credentials Data Model v2.0",
      "text": "Ecosystem Compatibility",
      "url": "https://www.w3.org/TR/vc-data-model-2.0/#ecosystem-compatibility"
    }
  },
  "#ecosystem-overview": {
    "current": {
      "number": "1.2",
      "spec": "Verifiable Credentials Data Model v2.0",
      "text": "Ecosystem Overview",
      "url": "https://w3c.github.io/vc-data-model/#ecosystem-overview"
    },
    "snapshot": {
      "number": "1.2",
      "spec": "Verifiable Credentials Data Model v2.0",
      "text": "Ecosystem Overview",
      "url": "https://www.w3.org/TR/vc-data-model-2.0/#ecosystem-overview"
    }
  },
  "#enveloped-verifiable-credentials": {
    "current": {
      "number": "",
      "spec": "Verifiable Credentials Data Model v2.0",
      "text": "Enveloped Verifiable Credentials",
      "url": "https://w3c.github.io/vc-data-model/#enveloped-verifiable-credentials"
    },
    "snapshot": {
      "number": "",
      "spec": "Verifiable Credentials Data Model v2.0",
      "text": "Enveloped Verifiable Credentials",
      "url": "https://www.w3.org/TR/vc-data-model-2.0/#enveloped-verifiable-credentials"
    }
  },
  "#enveloped-verifiable-presentations": {
    "current": {
      "number": "",
      "spec": "Verifiable Credentials Data Model v2.0",
      "text": "Enveloped Verifiable Presentations",
      "url": "https://w3c.github.io/vc-data-model/#enveloped-verifiable-presentations"
    },
    "snapshot": {
      "number": "",
      "spec": "Verifiable Credentials Data Model v2.0",
      "text": "Enveloped Verifiable Presentations",
      "url": "https://www.w3.org/TR/vc-data-model-2.0/#enveloped-verifiable-presentations"
    }
  },
  "#evidence": {
    "current": {
      "number": "5.6",
      "spec": "Verifiable Credentials Data Model v2.0",
      "text": "Evidence",
      "url": "https://w3c.github.io/vc-data-model/#evidence"
    },
    "snapshot": {
      "number": "5.6",
      "spec": "Verifiable Credentials Data Model v2.0",
      "text": "Evidence",
      "url": "https://www.w3.org/TR/vc-data-model-2.0/#evidence"
    }
  },
  "#extensibility": {
    "current": {
      "number": "5.2",
      "spec": "Verifiable Credentials Data Model v2.0",
      "text": "Extensibility",
      "url": "https://w3c.github.io/vc-data-model/#extensibility"
    },
    "snapshot": {
      "number": "5.2",
      "spec": "Verifiable Credentials Data Model v2.0",
      "text": "Extensibility",
      "url": "https://www.w3.org/TR/vc-data-model-2.0/#extensibility"
    }
  },
  "#favor-abstract-claims": {
    "current": {
      "number": "8.8",
      "spec": "Verifiable Credentials Data Model v2.0",
      "text": "Favor Abstract Claims",
      "url": "https://w3c.github.io/vc-data-model/#favor-abstract-claims"
    },
    "snapshot": {
      "number": "8.8",
      "spec": "Verifiable Credentials Data Model v2.0",
      "text": "Favor Abstract Claims",
      "url": "https://www.w3.org/TR/vc-data-model-2.0/#favor-abstract-claims"
    }
  },
  "#fitness-for-purpose": {
    "current": {
      "number": "A.10",
      "spec": "Verifiable Credentials Data Model v2.0",
      "text": "Fitness for Purpose",
      "url": "https://w3c.github.io/vc-data-model/#fitness-for-purpose"
    },
    "snapshot": {
      "number": "A.10",
      "spec": "Verifiable Credentials Data Model v2.0",
      "text": "Fitness for Purpose",
      "url": "https://www.w3.org/TR/vc-data-model-2.0/#fitness-for-purpose"
    }
  },
  "#frequency-of-claim-issuance": {
    "current": {
      "number": "8.18",
      "spec": "Verifiable Credentials Data Model v2.0",
      "text": "Frequency of Claim Issuance",
      "url": "https://w3c.github.io/vc-data-model/#frequency-of-claim-issuance"
    },
    "snapshot": {
      "number": "8.18",
      "spec": "Verifiable Credentials Data Model v2.0",
      "text": "Frequency of Claim Issuance",
      "url": "https://www.w3.org/TR/vc-data-model-2.0/#frequency-of-claim-issuance"
    }
  },
  "#getting-started": {
    "current": {
      "number": "4.1",
      "spec": "Verifiable Credentials Data Model v2.0",
      "text": "Getting Started",
      "url": "https://w3c.github.io/vc-data-model/#getting-started"
    },
    "snapshot": {
      "number": "4.1",
      "spec": "Verifiable Credentials Data Model v2.0",
      "text": "Getting Started",
      "url": "https://www.w3.org/TR/vc-data-model-2.0/#getting-started"
    }
  },
  "#highly-dynamic-information": {
    "current": {
      "number": "9.7",
      "spec": "Verifiable Credentials Data Model v2.0",
      "text": "Highly Dynamic Information",
      "url": "https://w3c.github.io/vc-data-model/#highly-dynamic-information"
    },
    "snapshot": {
      "number": "9.7",
      "spec": "Verifiable Credentials Data Model v2.0",
      "text": "Highly Dynamic Information",
      "url": "https://www.w3.org/TR/vc-data-model-2.0/#highly-dynamic-information"
    }
  },
  "#holder": {
    "current": {
      "number": "A.4",
      "spec": "Verifiable Credentials Data Model v2.0",
      "text": "Holder",
      "url": "https://w3c.github.io/vc-data-model/#holder"
    },
    "snapshot": {
      "number": "A.4",
      "spec": "Verifiable Credentials Data Model v2.0",
      "text": "Holder",
      "url": "https://www.w3.org/TR/vc-data-model-2.0/#holder"
    }
  },
  "#iana-considerations": {
    "current": {
      "number": "C",
      "spec": "Verifiable Credentials Data Model v2.0",
      "text": "IANA Considerations",
      "url": "https://w3c.github.io/vc-data-model/#iana-considerations"
    },
    "snapshot": {
      "number": "C",
      "spec": "Verifiable Credentials Data Model v2.0",
      "text": "IANA Considerations",
      "url": "https://www.w3.org/TR/vc-data-model-2.0/#iana-considerations"
    }
  },
  "#identifier-based-correlation": {
    "current": {
      "number": "8.4",
      "spec": "Verifiable Credentials Data Model v2.0",
      "text": "Identifier-Based Correlation",
      "url": "https://w3c.github.io/vc-data-model/#identifier-based-correlation"
    },
    "snapshot": {
      "number": "8.4",
      "spec": "Verifiable Credentials Data Model v2.0",
      "text": "Identifier-Based Correlation",
      "url": "https://www.w3.org/TR/vc-data-model-2.0/#identifier-based-correlation"
    }
  },
  "#identifiers": {
    "current": {
      "number": "4.4",
      "spec": "Verifiable Credentials Data Model v2.0",
      "text": "Identifiers",
      "url": "https://w3c.github.io/vc-data-model/#identifiers"
    },
    "snapshot": {
      "number": "4.4",
      "spec": "Verifiable Credentials Data Model v2.0",
      "text": "Identifiers",
      "url": "https://www.w3.org/TR/vc-data-model-2.0/#identifiers"
    }
  },
  "#inappropriate-use": {
    "current": {
      "number": "9.9.2",
      "spec": "Verifiable Credentials Data Model v2.0",
      "text": "Inappropriate Use",
      "url": "https://w3c.github.io/vc-data-model/#inappropriate-use"
    },
    "snapshot": {
      "number": "9.9.2",
      "spec": "Verifiable Credentials Data Model v2.0",
      "text": "Inappropriate Use",
      "url": "https://www.w3.org/TR/vc-data-model-2.0/#inappropriate-use"
    }
  },
  "#informative-references": {
    "current": {
      "number": "G.2",
      "spec": "Verifiable Credentials Data Model v2.0",
      "text": "Informative references",
      "url": "https://w3c.github.io/vc-data-model/#informative-references"
    },
    "snapshot": {
      "number": "G.2",
      "spec": "Verifiable Credentials Data Model v2.0",
      "text": "Informative references",
      "url": "https://www.w3.org/TR/vc-data-model-2.0/#informative-references"
    }
  },
  "#integrity-of-related-resources": {
    "current": {
      "number": "5.3",
      "spec": "Verifiable Credentials Data Model v2.0",
      "text": "Integrity of Related Resources",
      "url": "https://w3c.github.io/vc-data-model/#integrity-of-related-resources"
    },
    "snapshot": {
      "number": "5.3",
      "spec": "Verifiable Credentials Data Model v2.0",
      "text": "Integrity of Related Resources",
      "url": "https://www.w3.org/TR/vc-data-model-2.0/#integrity-of-related-resources"
    }
  },
  "#internationalization-considerations": {
    "current": {
      "number": "",
      "spec": "Verifiable Credentials Data Model v2.0",
      "text": "11. Internationalization Considerations",
      "url": "https://w3c.github.io/vc-data-model/#internationalization-considerations"
    },
    "snapshot": {
      "number": "",
      "spec": "Verifiable Credentials Data Model v2.0",
      "text": "11. Internationalization Considerations",
      "url": "https://www.w3.org/TR/vc-data-model-2.0/#internationalization-considerations"
    }
  },
  "#introduction": {
    "current": {
      "number": "1",
      "spec": "Verifiable Credentials Data Model v2.0",
      "text": "Introduction",
      "url": "https://w3c.github.io/vc-data-model/#introduction"
    },
    "snapshot": {
      "number": "1",
      "spec": "Verifiable Credentials Data Model v2.0",
      "text": "Introduction",
      "url": "https://www.w3.org/TR/vc-data-model-2.0/#introduction"
    }
  },
  "#issuance-date": {
    "current": {
      "number": "A.5",
      "spec": "Verifiable Credentials Data Model v2.0",
      "text": "Issuance Date",
      "url": "https://w3c.github.io/vc-data-model/#issuance-date"
    },
    "snapshot": {
      "number": "A.5",
      "spec": "Verifiable Credentials Data Model v2.0",
      "text": "Issuance Date",
      "url": "https://www.w3.org/TR/vc-data-model-2.0/#issuance-date"
    }
  },
  "#issuer": {
    "current": {
      "number": "4.7",
      "spec": "Verifiable Credentials Data Model v2.0",
      "text": "Issuer",
      "url": "https://w3c.github.io/vc-data-model/#issuer"
    },
    "snapshot": {
      "number": "4.7",
      "spec": "Verifiable Credentials Data Model v2.0",
      "text": "Issuer",
      "url": "https://www.w3.org/TR/vc-data-model-2.0/#issuer"
    }
  },
  "#issuer-0": {
    "current": {
      "number": "A.3",
      "spec": "Verifiable Credentials Data Model v2.0",
      "text": "Issuer",
      "url": "https://w3c.github.io/vc-data-model/#issuer-0"
    },
    "snapshot": {
      "number": "A.3",
      "spec": "Verifiable Credentials Data Model v2.0",
      "text": "Issuer",
      "url": "https://www.w3.org/TR/vc-data-model-2.0/#issuer-0"
    }
  },
  "#issuer-cooperation-impacts-on-privacy": {
    "current": {
      "number": "8.21",
      "spec": "Verifiable Credentials Data Model v2.0",
      "text": "Issuer Cooperation Impacts on Privacy",
      "url": "https://w3c.github.io/vc-data-model/#issuer-cooperation-impacts-on-privacy"
    },
    "snapshot": {
      "number": "8.21",
      "spec": "Verifiable Credentials Data Model v2.0",
      "text": "Issuer Cooperation Impacts on Privacy",
      "url": "https://www.w3.org/TR/vc-data-model-2.0/#issuer-cooperation-impacts-on-privacy"
    }
  },
  "#json-ld": {
    "current": {
      "number": "6.1",
      "spec": "Verifiable Credentials Data Model v2.0",
      "text": "JSON-LD",
      "url": "https://w3c.github.io/vc-data-model/#json-ld"
    },
    "snapshot": {
      "number": "6.1",
      "spec": "Verifiable Credentials Data Model v2.0",
      "text": "JSON-LD",
      "url": "https://www.w3.org/TR/vc-data-model-2.0/#json-ld"
    }
  },
  "#key-management": {
    "current": {
      "number": "9.2",
      "spec": "Verifiable Credentials Data Model v2.0",
      "text": "Key Management",
      "url": "https://w3c.github.io/vc-data-model/#key-management"
    },
    "snapshot": {
      "number": "9.2",
      "spec": "Verifiable Credentials Data Model v2.0",
      "text": "Key Management",
      "url": "https://www.w3.org/TR/vc-data-model-2.0/#key-management"
    }
  },
  "#language-and-base-direction": {
    "current": {
      "number": "11.1",
      "spec": "Verifiable Credentials Data Model v2.0",
      "text": "Language and Base Direction",
      "url": "https://w3c.github.io/vc-data-model/#language-and-base-direction"
    },
    "snapshot": {
      "number": "11.1",
      "spec": "Verifiable Credentials Data Model v2.0",
      "text": "Language and Base Direction",
      "url": "https://www.w3.org/TR/vc-data-model-2.0/#language-and-base-direction"
    }
  },
  "#legal-processes": {
    "current": {
      "number": "8.15",
      "spec": "Verifiable Credentials Data Model v2.0",
      "text": "Legal Processes",
      "url": "https://w3c.github.io/vc-data-model/#legal-processes"
    },
    "snapshot": {
      "number": "8.15",
      "spec": "Verifiable Credentials Data Model v2.0",
      "text": "Legal Processes",
      "url": "https://www.w3.org/TR/vc-data-model-2.0/#legal-processes"
    }
  },
  "#lists-and-arrays": {
    "current": {
      "number": "",
      "spec": "Verifiable Credentials Data Model v2.0",
      "text": "Lists and Arrays",
      "url": "https://w3c.github.io/vc-data-model/#lists-and-arrays"
    },
    "snapshot": {
      "number": "",
      "spec": "Verifiable Credentials Data Model v2.0",
      "text": "Lists and Arrays",
      "url": "https://www.w3.org/TR/vc-data-model-2.0/#lists-and-arrays"
    }
  },
  "#man-in-the-middle-mitm-attack": {
    "current": {
      "number": "9.5.1",
      "spec": "Verifiable Credentials Data Model v2.0",
      "text": "Man-in-the-Middle (MITM) Attack",
      "url": "https://w3c.github.io/vc-data-model/#man-in-the-middle-mitm-attack"
    },
    "snapshot": {
      "number": "9.5.1",
      "spec": "Verifiable Credentials Data Model v2.0",
      "text": "Man-in-the-Middle (MITM) Attack",
      "url": "https://www.w3.org/TR/vc-data-model-2.0/#man-in-the-middle-mitm-attack"
    }
  },
  "#man-in-the-middle-mitm-replay-and-cloning-attacks": {
    "current": {
      "number": "9.5",
      "spec": "Verifiable Credentials Data Model v2.0",
      "text": "Man-in-the-Middle (MITM), Replay, and Cloning Attacks",
      "url": "https://w3c.github.io/vc-data-model/#man-in-the-middle-mitm-replay-and-cloning-attacks"
    },
    "snapshot": {
      "number": "9.5",
      "spec": "Verifiable Credentials Data Model v2.0",
      "text": "Man-in-the-Middle (MITM), Replay, and Cloning Attacks",
      "url": "https://www.w3.org/TR/vc-data-model-2.0/#man-in-the-middle-mitm-replay-and-cloning-attacks"
    }
  },
  "#media-type-precision": {
    "current": {
      "number": "",
      "spec": "Verifiable Credentials Data Model v2.0",
      "text": "Media Type Precision",
      "url": "https://w3c.github.io/vc-data-model/#media-type-precision"
    },
    "snapshot": {
      "number": "",
      "spec": "Verifiable Credentials Data Model v2.0",
      "text": "Media Type Precision",
      "url": "https://www.w3.org/TR/vc-data-model-2.0/#media-type-precision"
    }
  },
  "#media-types": {
    "current": {
      "number": "6.2",
      "spec": "Verifiable Credentials Data Model v2.0",
      "text": "Media Types",
      "url": "https://w3c.github.io/vc-data-model/#media-types"
    },
    "snapshot": {
      "number": "6.2",
      "spec": "Verifiable Credentials Data Model v2.0",
      "text": "Media Types",
      "url": "https://www.w3.org/TR/vc-data-model-2.0/#media-types"
    }
  },
  "#metadata-based-correlation": {
    "current": {
      "number": "8.6",
      "spec": "Verifiable Credentials Data Model v2.0",
      "text": "Metadata-based Correlation",
      "url": "https://w3c.github.io/vc-data-model/#metadata-based-correlation"
    },
    "snapshot": {
      "number": "8.6",
      "spec": "Verifiable Credentials Data Model v2.0",
      "text": "Metadata-based Correlation",
      "url": "https://www.w3.org/TR/vc-data-model-2.0/#metadata-based-correlation"
    }
  },
  "#names-and-descriptions": {
    "current": {
      "number": "4.6",
      "spec": "Verifiable Credentials Data Model v2.0",
      "text": "Names and Descriptions",
      "url": "https://w3c.github.io/vc-data-model/#names-and-descriptions"
    },
    "snapshot": {
      "number": "4.6",
      "spec": "Verifiable Credentials Data Model v2.0",
      "text": "Names and Descriptions",
      "url": "https://www.w3.org/TR/vc-data-model-2.0/#names-and-descriptions"
    }
  },
  "#normative-references": {
    "current": {
      "number": "G.1",
      "spec": "Verifiable Credentials Data Model v2.0",
      "text": "Normative references",
      "url": "https://w3c.github.io/vc-data-model/#normative-references"
    },
    "snapshot": {
      "number": "G.1",
      "spec": "Verifiable Credentials Data Model v2.0",
      "text": "Normative references",
      "url": "https://www.w3.org/TR/vc-data-model-2.0/#normative-references"
    }
  },
  "#notable-json-ld-features": {
    "current": {
      "number": "",
      "spec": "Verifiable Credentials Data Model v2.0",
      "text": "Notable JSON-LD Features",
      "url": "https://w3c.github.io/vc-data-model/#notable-json-ld-features"
    },
    "snapshot": {
      "number": "",
      "spec": "Verifiable Credentials Data Model v2.0",
      "text": "Notable JSON-LD Features",
      "url": "https://www.w3.org/TR/vc-data-model-2.0/#notable-json-ld-features"
    }
  },
  "#patterns-of-use": {
    "current": {
      "number": "8.14",
      "spec": "Verifiable Credentials Data Model v2.0",
      "text": "Patterns of Use",
      "url": "https://w3c.github.io/vc-data-model/#patterns-of-use"
    },
    "snapshot": {
      "number": "8.14",
      "spec": "Verifiable Credentials Data Model v2.0",
      "text": "Patterns of Use",
      "url": "https://www.w3.org/TR/vc-data-model-2.0/#patterns-of-use"
    }
  },
  "#personally-identifiable-information": {
    "current": {
      "number": "8.3",
      "spec": "Verifiable Credentials Data Model v2.0",
      "text": "Personally Identifiable Information",
      "url": "https://w3c.github.io/vc-data-model/#personally-identifiable-information"
    },
    "snapshot": {
      "number": "8.3",
      "spec": "Verifiable Credentials Data Model v2.0",
      "text": "Personally Identifiable Information",
      "url": "https://www.w3.org/TR/vc-data-model-2.0/#personally-identifiable-information"
    }
  },
  "#prefer-single-use-credentials": {
    "current": {
      "number": "8.19",
      "spec": "Verifiable Credentials Data Model v2.0",
      "text": "Prefer Single-Use Credentials",
      "url": "https://w3c.github.io/vc-data-model/#prefer-single-use-credentials"
    },
    "snapshot": {
      "number": "8.19",
      "spec": "Verifiable Credentials Data Model v2.0",
      "text": "Prefer Single-Use Credentials",
      "url": "https://www.w3.org/TR/vc-data-model-2.0/#prefer-single-use-credentials"
    }
  },
  "#presentations": {
    "current": {
      "number": "3.3",
      "spec": "Verifiable Credentials Data Model v2.0",
      "text": "Presentations",
      "url": "https://w3c.github.io/vc-data-model/#presentations"
    },
    "snapshot": {
      "number": "3.3",
      "spec": "Verifiable Credentials Data Model v2.0",
      "text": "Presentations",
      "url": "https://www.w3.org/TR/vc-data-model-2.0/#presentations"
    }
  },
  "#presentations-including-holder-claims": {
    "current": {
      "number": "",
      "spec": "Verifiable Credentials Data Model v2.0",
      "text": "Presentations Including Holder Claims",
      "url": "https://w3c.github.io/vc-data-model/#presentations-including-holder-claims"
    },
    "snapshot": {
      "number": "",
      "spec": "Verifiable Credentials Data Model v2.0",
      "text": "Presentations Including Holder Claims",
      "url": "https://www.w3.org/TR/vc-data-model-2.0/#presentations-including-holder-claims"
    }
  },
  "#presentations-using-derived-credentials": {
    "current": {
      "number": "",
      "spec": "Verifiable Credentials Data Model v2.0",
      "text": "Presentations Using Derived Credentials",
      "url": "https://w3c.github.io/vc-data-model/#presentations-using-derived-credentials"
    },
    "snapshot": {
      "number": "",
      "spec": "Verifiable Credentials Data Model v2.0",
      "text": "Presentations Using Derived Credentials",
      "url": "https://www.w3.org/TR/vc-data-model-2.0/#presentations-using-derived-credentials"
    }
  },
  "#privacy-considerations": {
    "current": {
      "number": "8",
      "spec": "Verifiable Credentials Data Model v2.0",
      "text": "Privacy Considerations",
      "url": "https://w3c.github.io/vc-data-model/#privacy-considerations"
    },
    "snapshot": {
      "number": "8",
      "spec": "Verifiable Credentials Data Model v2.0",
      "text": "Privacy Considerations",
      "url": "https://www.w3.org/TR/vc-data-model-2.0/#privacy-considerations"
    }
  },
  "#private-browsing": {
    "current": {
      "number": "8.20",
      "spec": "Verifiable Credentials Data Model v2.0",
      "text": "Private Browsing",
      "url": "https://w3c.github.io/vc-data-model/#private-browsing"
    },
    "snapshot": {
      "number": "8.20",
      "spec": "Verifiable Credentials Data Model v2.0",
      "text": "Private Browsing",
      "url": "https://www.w3.org/TR/vc-data-model-2.0/#private-browsing"
    }
  },
  "#problem-details": {
    "current": {
      "number": "7.2",
      "spec": "Verifiable Credentials Data Model v2.0",
      "text": "Problem Details",
      "url": "https://w3c.github.io/vc-data-model/#problem-details"
    },
    "snapshot": {
      "number": "7.2",
      "spec": "Verifiable Credentials Data Model v2.0",
      "text": "Problem Details",
      "url": "https://www.w3.org/TR/vc-data-model-2.0/#problem-details"
    }
  },
  "#proofs-signatures": {
    "current": {
      "number": "A.6",
      "spec": "Verifiable Credentials Data Model v2.0",
      "text": "Proofs (Signatures)",
      "url": "https://w3c.github.io/vc-data-model/#proofs-signatures"
    },
    "snapshot": {
      "number": "A.6",
      "spec": "Verifiable Credentials Data Model v2.0",
      "text": "Proofs (Signatures)",
      "url": "https://www.w3.org/TR/vc-data-model-2.0/#proofs-signatures"
    }
  },
  "#providing-default-language-and-direction": {
    "current": {
      "number": "11.2",
      "spec": "Verifiable Credentials Data Model v2.0",
      "text": "Providing Default Language and Direction",
      "url": "https://w3c.github.io/vc-data-model/#providing-default-language-and-direction"
    },
    "snapshot": {
      "number": "11.2",
      "spec": "Verifiable Credentials Data Model v2.0",
      "text": "Providing Default Language and Direction",
      "url": "https://www.w3.org/TR/vc-data-model-2.0/#providing-default-language-and-direction"
    }
  },
  "#references": {
    "current": {
      "number": "G",
      "spec": "Verifiable Credentials Data Model v2.0",
      "text": "References",
      "url": "https://w3c.github.io/vc-data-model/#references"
    },
    "snapshot": {
      "number": "G",
      "spec": "Verifiable Credentials Data Model v2.0",
      "text": "References",
      "url": "https://www.w3.org/TR/vc-data-model-2.0/#references"
    }
  },
  "#refreshing": {
    "current": {
      "number": "5.4",
      "spec": "Verifiable Credentials Data Model v2.0",
      "text": "Refreshing",
      "url": "https://w3c.github.io/vc-data-model/#refreshing"
    },
    "snapshot": {
      "number": "5.4",
      "spec": "Verifiable Credentials Data Model v2.0",
      "text": "Refreshing",
      "url": "https://www.w3.org/TR/vc-data-model-2.0/#refreshing"
    }
  },
  "#replay-attack": {
    "current": {
      "number": "9.5.2",
      "spec": "Verifiable Credentials Data Model v2.0",
      "text": "Replay Attack",
      "url": "https://w3c.github.io/vc-data-model/#replay-attack"
    },
    "snapshot": {
      "number": "9.5.2",
      "spec": "Verifiable Credentials Data Model v2.0",
      "text": "Replay Attack",
      "url": "https://www.w3.org/TR/vc-data-model-2.0/#replay-attack"
    }
  },
  "#representing-time": {
    "current": {
      "number": "5.8",
      "spec": "Verifiable Credentials Data Model v2.0",
      "text": "Representing Time",
      "url": "https://w3c.github.io/vc-data-model/#representing-time"
    },
    "snapshot": {
      "number": "5.8",
      "spec": "Verifiable Credentials Data Model v2.0",
      "text": "Representing Time",
      "url": "https://www.w3.org/TR/vc-data-model-2.0/#representing-time"
    }
  },
  "#reserved-extension-points": {
    "current": {
      "number": "5.10",
      "spec": "Verifiable Credentials Data Model v2.0",
      "text": "Reserved Extension Points",
      "url": "https://w3c.github.io/vc-data-model/#reserved-extension-points"
    },
    "snapshot": {
      "number": "5.10",
      "spec": "Verifiable Credentials Data Model v2.0",
      "text": "Reserved Extension Points",
      "url": "https://www.w3.org/TR/vc-data-model-2.0/#reserved-extension-points"
    }
  },
  "#restrictions-on-json-ld": {
    "current": {
      "number": "",
      "spec": "Verifiable Credentials Data Model v2.0",
      "text": "Restrictions on JSON-LD",
      "url": "https://w3c.github.io/vc-data-model/#restrictions-on-json-ld"
    },
    "snapshot": {
      "number": "",
      "spec": "Verifiable Credentials Data Model v2.0",
      "text": "Restrictions on JSON-LD",
      "url": "https://www.w3.org/TR/vc-data-model-2.0/#restrictions-on-json-ld"
    }
  },
  "#revision-history": {
    "current": {
      "number": "E",
      "spec": "Verifiable Credentials Data Model v2.0",
      "text": "Revision History",
      "url": "https://w3c.github.io/vc-data-model/#revision-history"
    },
    "snapshot": {
      "number": "E",
      "spec": "Verifiable Credentials Data Model v2.0",
      "text": "Revision History",
      "url": "https://www.w3.org/TR/vc-data-model-2.0/#revision-history"
    }
  },
  "#schema": {
    "current": {
      "number": "A.9",
      "spec": "Verifiable Credentials Data Model v2.0",
      "text": "Schema",
      "url": "https://w3c.github.io/vc-data-model/#schema"
    },
    "snapshot": {
      "number": "A.9",
      "spec": "Verifiable Credentials Data Model v2.0",
      "text": "Schema",
      "url": "https://www.w3.org/TR/vc-data-model-2.0/#schema"
    }
  },
  "#sd-jwt-claim--IMTVfAXrGxpv5A0G0k7jJpZjsryEO9dU7lOME6bLYQ": {
    "current": {
      "number": "",
      "spec": "Verifiable Credentials Data Model v2.0",
      "text": "Claim: type",
      "url": "https://w3c.github.io/vc-data-model/#sd-jwt-claim--IMTVfAXrGxpv5A0G0k7jJpZjsryEO9dU7lOME6bLYQ"
    }
  },
  "#sd-jwt-claim-1WzLTHt7mQSKsbpei8RmmjMnCopd7bwcK1IBBHlKg2E": {
    "current": {
      "number": "",
      "spec": "Verifiable Credentials Data Model v2.0",
      "text": "Claim: id",
      "url": "https://w3c.github.io/vc-data-model/#sd-jwt-claim-1WzLTHt7mQSKsbpei8RmmjMnCopd7bwcK1IBBHlKg2E"
    }
  },
  "#sd-jwt-claim-2lBBeAOTvuHczsho-5a1lgHpV8C9hrYZr7cCD1GAHe8": {
    "current": {
      "number": "",
      "spec": "Verifiable Credentials Data Model v2.0",
      "text": "Claim: type",
      "url": "https://w3c.github.io/vc-data-model/#sd-jwt-claim-2lBBeAOTvuHczsho-5a1lgHpV8C9hrYZr7cCD1GAHe8"
    }
  },
  "#sd-jwt-claim-3-llajorkFpeZOdp0KoX2cKlBGeF38hwfa-SrdQlQrU": {
    "current": {
      "number": "",
      "spec": "Verifiable Credentials Data Model v2.0",
      "text": "Claim: type",
      "url": "https://w3c.github.io/vc-data-model/#sd-jwt-claim-3-llajorkFpeZOdp0KoX2cKlBGeF38hwfa-SrdQlQrU"
    }
  },
  "#sd-jwt-claim-3BVKoiC_VnfP3fhEspKhcyf4Ysja0lWoSfWCBs43PiI": {
    "current": {
      "number": "",
      "spec": "Verifiable Credentials Data Model v2.0",
      "text": "Claim: type",
      "url": "https://w3c.github.io/vc-data-model/#sd-jwt-claim-3BVKoiC_VnfP3fhEspKhcyf4Ysja0lWoSfWCBs43PiI"
    }
  },
  "#sd-jwt-claim-6IstGDTpjYRdhPjckRNHcmKRetOYlVsGy7D72pPhHhA": {
    "current": {
      "number": "",
      "spec": "Verifiable Credentials Data Model v2.0",
      "text": "Claim: type",
      "url": "https://w3c.github.io/vc-data-model/#sd-jwt-claim-6IstGDTpjYRdhPjckRNHcmKRetOYlVsGy7D72pPhHhA"
    }
  },
  "#sd-jwt-claim-6V26j4pGltFgTHPenKDLjEP--aMjtT7701sooojAq9E": {
    "snapshot": {
      "number": "",
      "spec": "Verifiable Credentials Data Model v2.0",
      "text": "Claim: id",
      "url": "https://www.w3.org/TR/vc-data-model-2.0/#sd-jwt-claim-6V26j4pGltFgTHPenKDLjEP--aMjtT7701sooojAq9E"
    }
  },
  "#sd-jwt-claim-8WzFUXkmHzCw9Gkg6x72b3UyDFZII9g-nz3l1AcBz-4": {
    "current": {
      "number": "",
      "spec": "Verifiable Credentials Data Model v2.0",
      "text": "Claim: type",
      "url": "https://w3c.github.io/vc-data-model/#sd-jwt-claim-8WzFUXkmHzCw9Gkg6x72b3UyDFZII9g-nz3l1AcBz-4"
    }
  },
  "#sd-jwt-claim-9NlzezuXgE5qr_2btVJ0lymC7hal4GLjjjExN8WYs_0": {
    "snapshot": {
      "number": "",
      "spec": "Verifiable Credentials Data Model v2.0",
      "text": "Claim: type",
      "url": "https://www.w3.org/TR/vc-data-model-2.0/#sd-jwt-claim-9NlzezuXgE5qr_2btVJ0lymC7hal4GLjjjExN8WYs_0"
    }
  },
  "#sd-jwt-claim-Ai_aoHwqG2c4RmoO7iF7h6QQAyRM0F8Zz4cg6xEbXIo": {
    "current": {
      "number": "",
      "spec": "Verifiable Credentials Data Model v2.0",
      "text": "Claim: id",
      "url": "https://w3c.github.io/vc-data-model/#sd-jwt-claim-Ai_aoHwqG2c4RmoO7iF7h6QQAyRM0F8Zz4cg6xEbXIo"
    }
  },
  "#sd-jwt-claim-B0fSmsUgsxLIbESJUQdNh_-N-ENMik3pdYNdCgCR4RQ": {
    "snapshot": {
      "number": "",
      "spec": "Verifiable Credentials Data Model v2.0",
      "text": "Claim: type",
      "url": "https://www.w3.org/TR/vc-data-model-2.0/#sd-jwt-claim-B0fSmsUgsxLIbESJUQdNh_-N-ENMik3pdYNdCgCR4RQ"
    }
  },
  "#sd-jwt-claim-CI-6CQPdgrEpkAOhV_itIxXs1Wf60hWY6l3pbR1R0hE": {
    "snapshot": {
      "number": "",
      "spec": "Verifiable Credentials Data Model v2.0",
      "text": "Claim: type",
      "url": "https://www.w3.org/TR/vc-data-model-2.0/#sd-jwt-claim-CI-6CQPdgrEpkAOhV_itIxXs1Wf60hWY6l3pbR1R0hE"
    }
  },
  "#sd-jwt-claim-DakP5BjdYhX9K60zN8asWQrcvXkSNvz3SyIoDCQ_y6A": {
    "snapshot": {
      "number": "",
      "spec": "Verifiable Credentials Data Model v2.0",
      "text": "Claim: id",
      "url": "https://www.w3.org/TR/vc-data-model-2.0/#sd-jwt-claim-DakP5BjdYhX9K60zN8asWQrcvXkSNvz3SyIoDCQ_y6A"
    }
  },
  "#sd-jwt-claim-Dqei-sEM4FdaxXby2_FnbA9bp2YwEOFh8mZN9_9GANY": {
    "snapshot": {
      "number": "",
      "spec": "Verifiable Credentials Data Model v2.0",
      "text": "Claim: type",
      "url": "https://www.w3.org/TR/vc-data-model-2.0/#sd-jwt-claim-Dqei-sEM4FdaxXby2_FnbA9bp2YwEOFh8mZN9_9GANY"
    }
  },
  "#sd-jwt-claim-EwETmC9_da-a2K1ql0L-51M5EcrtYKHdY9M49Fh69N0": {
    "snapshot": {
      "number": "",
      "spec": "Verifiable Credentials Data Model v2.0",
      "text": "Claim: id",
      "url": "https://www.w3.org/TR/vc-data-model-2.0/#sd-jwt-claim-EwETmC9_da-a2K1ql0L-51M5EcrtYKHdY9M49Fh69N0"
    }
  },
  "#sd-jwt-claim-FycDdtdikkK-xUUPrJC0u86r2X53gA8y7Ft3NbM1EUI": {
    "current": {
      "number": "",
      "spec": "Verifiable Credentials Data Model v2.0",
      "text": "Claim: type",
      "url": "https://w3c.github.io/vc-data-model/#sd-jwt-claim-FycDdtdikkK-xUUPrJC0u86r2X53gA8y7Ft3NbM1EUI"
    }
  },
  "#sd-jwt-claim-G-zNdWI6SH8WdfaaZQmE5Ocxk6ZB-e3UAX9zJuRQdHU": {
    "snapshot": {
      "number": "",
      "spec": "Verifiable Credentials Data Model v2.0",
      "text": "Claim: id",
      "url": "https://www.w3.org/TR/vc-data-model-2.0/#sd-jwt-claim-G-zNdWI6SH8WdfaaZQmE5Ocxk6ZB-e3UAX9zJuRQdHU"
    }
  },
  "#sd-jwt-claim-GCci6qhRTLxVLKOjV45U-KumYwk9i8nb6_A9YVuLXFY": {
    "current": {
      "number": "",
      "spec": "Verifiable Credentials Data Model v2.0",
      "text": "Claim: id",
      "url": "https://w3c.github.io/vc-data-model/#sd-jwt-claim-GCci6qhRTLxVLKOjV45U-KumYwk9i8nb6_A9YVuLXFY"
    }
  },
  "#sd-jwt-claim-H5jywPFwZwMDUhP-J16vwik-BJ-9pe1qMvmWjTmG_E4": {
    "current": {
      "number": "",
      "spec": "Verifiable Credentials Data Model v2.0",
      "text": "Claim: id",
      "url": "https://w3c.github.io/vc-data-model/#sd-jwt-claim-H5jywPFwZwMDUhP-J16vwik-BJ-9pe1qMvmWjTmG_E4"
    }
  },
  "#sd-jwt-claim-H81L6vRxIF-dhjLpWrHu70mwUd2al4TyNRdMGFCXW_8": {
    "snapshot": {
      "number": "",
      "spec": "Verifiable Credentials Data Model v2.0",
      "text": "Claim: id",
      "url": "https://www.w3.org/TR/vc-data-model-2.0/#sd-jwt-claim-H81L6vRxIF-dhjLpWrHu70mwUd2al4TyNRdMGFCXW_8"
    }
  },
  "#sd-jwt-claim-I50V6ZS1mV8GW8Z_NRM0pk10lyoU07mELuzTG5trufE": {
    "snapshot": {
      "number": "",
      "spec": "Verifiable Credentials Data Model v2.0",
      "text": "Claim: type",
      "url": "https://www.w3.org/TR/vc-data-model-2.0/#sd-jwt-claim-I50V6ZS1mV8GW8Z_NRM0pk10lyoU07mELuzTG5trufE"
    }
  },
  "#sd-jwt-claim-KK280DxNW90ldKem6DX20dTIaNoOYuF41h_TqtDGwYE": {
    "current": {
      "number": "",
      "spec": "Verifiable Credentials Data Model v2.0",
      "text": "Claim: id",
      "url": "https://w3c.github.io/vc-data-model/#sd-jwt-claim-KK280DxNW90ldKem6DX20dTIaNoOYuF41h_TqtDGwYE"
    }
  },
  "#sd-jwt-claim-LKwzYPBTOrwHfXZyNDIoGfOTd-fQ847_68uo0r38cB4": {
    "snapshot": {
      "number": "",
      "spec": "Verifiable Credentials Data Model v2.0",
      "text": "Claim: type",
      "url": "https://www.w3.org/TR/vc-data-model-2.0/#sd-jwt-claim-LKwzYPBTOrwHfXZyNDIoGfOTd-fQ847_68uo0r38cB4"
    }
  },
  "#sd-jwt-claim-LowkIiYpWvGGEd8Wk3xLj67tggp7DpKKXxln-VMzmJU": {
    "current": {
      "number": "",
      "spec": "Verifiable Credentials Data Model v2.0",
      "text": "Claim: id",
      "url": "https://w3c.github.io/vc-data-model/#sd-jwt-claim-LowkIiYpWvGGEd8Wk3xLj67tggp7DpKKXxln-VMzmJU"
    }
  },
  "#sd-jwt-claim-M8bgxNDXL3mb_TbKqK6B623PwafCqR-To-eUnfwWhRw": {
    "snapshot": {
      "number": "",
      "spec": "Verifiable Credentials Data Model v2.0",
      "text": "Claim: type",
      "url": "https://www.w3.org/TR/vc-data-model-2.0/#sd-jwt-claim-M8bgxNDXL3mb_TbKqK6B623PwafCqR-To-eUnfwWhRw"
    }
  },
  "#sd-jwt-claim-MaQCGH3y36tqPbQ5kiD02GtePfialYgVmYIOXy--_e8": {
    "current": {
      "number": "",
      "spec": "Verifiable Credentials Data Model v2.0",
      "text": "Claim: type",
      "url": "https://w3c.github.io/vc-data-model/#sd-jwt-claim-MaQCGH3y36tqPbQ5kiD02GtePfialYgVmYIOXy--_e8"
    }
  },
  "#sd-jwt-claim-MgCxUmfqJQ_-8kpq3_k9kEHKQaNXmhkdMBgvwYppN_A": {
    "snapshot": {
      "number": "",
      "spec": "Verifiable Credentials Data Model v2.0",
      "text": "Claim: type",
      "url": "https://www.w3.org/TR/vc-data-model-2.0/#sd-jwt-claim-MgCxUmfqJQ_-8kpq3_k9kEHKQaNXmhkdMBgvwYppN_A"
    }
  },
  "#sd-jwt-claim-P66dLjTUyb4HlPg5wjhwdE5JFcO7o0Hq-thkxSazGAQ": {
    "current": {
      "number": "",
      "spec": "Verifiable Credentials Data Model v2.0",
      "text": "Claim: id",
      "url": "https://w3c.github.io/vc-data-model/#sd-jwt-claim-P66dLjTUyb4HlPg5wjhwdE5JFcO7o0Hq-thkxSazGAQ"
    }
  },
  "#sd-jwt-claim-POP3_CDKwyqWMaJNvTqEsPVTNFQyK8n3XvFlUwcbbGk": {
    "snapshot": {
      "number": "",
      "spec": "Verifiable Credentials Data Model v2.0",
      "text": "Claim: id",
      "url": "https://www.w3.org/TR/vc-data-model-2.0/#sd-jwt-claim-POP3_CDKwyqWMaJNvTqEsPVTNFQyK8n3XvFlUwcbbGk"
    }
  },
  "#sd-jwt-claim-Pd0RzeamjiD7Tx9skTgQoc01h4o1n6MlSrhU28RL6eU": {
    "snapshot": {
      "number": "",
      "spec": "Verifiable Credentials Data Model v2.0",
      "text": "Claim: id",
      "url": "https://www.w3.org/TR/vc-data-model-2.0/#sd-jwt-claim-Pd0RzeamjiD7Tx9skTgQoc01h4o1n6MlSrhU28RL6eU"
    }
  },
  "#sd-jwt-claim-PdJ9zVFaUrE-lu9pxH5lXusOBKRClygSdwzyw9L5ArM": {
    "snapshot": {
      "number": "",
      "spec": "Verifiable Credentials Data Model v2.0",
      "text": "Claim: type",
      "url": "https://www.w3.org/TR/vc-data-model-2.0/#sd-jwt-claim-PdJ9zVFaUrE-lu9pxH5lXusOBKRClygSdwzyw9L5ArM"
    }
  },
  "#sd-jwt-claim-Qa5HqNuvcb2YPAMsOeUvn57813BtNBXW5SjFikOnphE": {
    "snapshot": {
      "number": "",
      "spec": "Verifiable Credentials Data Model v2.0",
      "text": "Claim: type",
      "url": "https://www.w3.org/TR/vc-data-model-2.0/#sd-jwt-claim-Qa5HqNuvcb2YPAMsOeUvn57813BtNBXW5SjFikOnphE"
    }
  },
  "#sd-jwt-claim-QuN2PtPJwIx75XJ7pka8xYMNiLv-vai6zjeaa-VggC8": {
    "current": {
      "number": "",
      "spec": "Verifiable Credentials Data Model v2.0",
      "text": "Claim: type",
      "url": "https://w3c.github.io/vc-data-model/#sd-jwt-claim-QuN2PtPJwIx75XJ7pka8xYMNiLv-vai6zjeaa-VggC8"
    }
  },
  "#sd-jwt-claim-RuXEi7H1e8XFTYlTxNh_BZ97mMobbN1PfIuTxSNrvNw": {
    "snapshot": {
      "number": "",
      "spec": "Verifiable Credentials Data Model v2.0",
      "text": "Claim: id",
      "url": "https://www.w3.org/TR/vc-data-model-2.0/#sd-jwt-claim-RuXEi7H1e8XFTYlTxNh_BZ97mMobbN1PfIuTxSNrvNw"
    }
  },
  "#sd-jwt-claim-SBRbr-rzZ-CPdxpGG6ASOQIxzzvPT59zh_Sy20Z4ZSE": {
    "snapshot": {
      "number": "",
      "spec": "Verifiable Credentials Data Model v2.0",
      "text": "Claim: type",
      "url": "https://www.w3.org/TR/vc-data-model-2.0/#sd-jwt-claim-SBRbr-rzZ-CPdxpGG6ASOQIxzzvPT59zh_Sy20Z4ZSE"
    }
  },
  "#sd-jwt-claim-TI6nFEft4AW_scoAkkDuK8XAxQrlTzDgufrwn7KvNbM": {
    "snapshot": {
      "number": "",
      "spec": "Verifiable Credentials Data Model v2.0",
      "text": "Claim: type",
      "url": "https://www.w3.org/TR/vc-data-model-2.0/#sd-jwt-claim-TI6nFEft4AW_scoAkkDuK8XAxQrlTzDgufrwn7KvNbM"
    }
  },
  "#sd-jwt-claim-TNA35RkJuKhGM1stpgrZbjluX1s0YChBKVoNBo0ZYoA": {
    "current": {
      "number": "",
      "spec": "Verifiable Credentials Data Model v2.0",
      "text": "Claim: id",
      "url": "https://w3c.github.io/vc-data-model/#sd-jwt-claim-TNA35RkJuKhGM1stpgrZbjluX1s0YChBKVoNBo0ZYoA"
    }
  },
  "#sd-jwt-claim-WDCaYpuvH5SbofBh4RvPr8Ipni7O6zoH5hqYHFPoXwY": {
    "snapshot": {
      "number": "",
      "spec": "Verifiable Credentials Data Model v2.0",
      "text": "Claim: id",
      "url": "https://www.w3.org/TR/vc-data-model-2.0/#sd-jwt-claim-WDCaYpuvH5SbofBh4RvPr8Ipni7O6zoH5hqYHFPoXwY"
    }
  },
  "#sd-jwt-claim-Y4tDZfdwHrLoy8ff37I9kdycB-VyCI8YWYGdfKTYPfc": {
    "snapshot": {
      "number": "",
      "spec": "Verifiable Credentials Data Model v2.0",
      "text": "Claim: id",
      "url": "https://www.w3.org/TR/vc-data-model-2.0/#sd-jwt-claim-Y4tDZfdwHrLoy8ff37I9kdycB-VyCI8YWYGdfKTYPfc"
    }
  },
  "#sd-jwt-claim-Yb_2fhWynYRdNxbONji5p-_MaiRqTPSkhq-3rXjUFEU": {
    "current": {
      "number": "",
      "spec": "Verifiable Credentials Data Model v2.0",
      "text": "Claim: id",
      "url": "https://w3c.github.io/vc-data-model/#sd-jwt-claim-Yb_2fhWynYRdNxbONji5p-_MaiRqTPSkhq-3rXjUFEU"
    }
  },
  "#sd-jwt-claim-YuWBFYzuJ-8sbc4QF82L43sqz-BT8Scrg5arULf3dtA": {
    "snapshot": {
      "number": "",
      "spec": "Verifiable Credentials Data Model v2.0",
      "text": "Claim: id",
      "url": "https://www.w3.org/TR/vc-data-model-2.0/#sd-jwt-claim-YuWBFYzuJ-8sbc4QF82L43sqz-BT8Scrg5arULf3dtA"
    }
  },
  "#sd-jwt-claim-YxlAXuIHyGbNxCrQ15rjLI4NXWHQ158OQP8c3Pl95sQ": {
    "snapshot": {
      "number": "",
      "spec": "Verifiable Credentials Data Model v2.0",
      "text": "Claim: type",
      "url": "https://www.w3.org/TR/vc-data-model-2.0/#sd-jwt-claim-YxlAXuIHyGbNxCrQ15rjLI4NXWHQ158OQP8c3Pl95sQ"
    }
  },
  "#sd-jwt-claim-Zf40XC2HLon3n1v5w48qA4RQe72rxaUX0AGgiOOXrrE": {
    "current": {
      "number": "",
      "spec": "Verifiable Credentials Data Model v2.0",
      "text": "Claim: type",
      "url": "https://w3c.github.io/vc-data-model/#sd-jwt-claim-Zf40XC2HLon3n1v5w48qA4RQe72rxaUX0AGgiOOXrrE"
    }
  },
  "#sd-jwt-claim-_YPaBegRY0Ggt-2juFKNXUlS0pEPgXzTR7tPkI9vTpI": {
    "snapshot": {
      "number": "",
      "spec": "Verifiable Credentials Data Model v2.0",
      "text": "Claim: id",
      "url": "https://www.w3.org/TR/vc-data-model-2.0/#sd-jwt-claim-_YPaBegRY0Ggt-2juFKNXUlS0pEPgXzTR7tPkI9vTpI"
    }
  },
  "#sd-jwt-claim-bdqQsIhoaqd0G16vD6iwVE5RcIS3BEz47wJfZwVy6ug": {
    "snapshot": {
      "number": "",
      "spec": "Verifiable Credentials Data Model v2.0",
      "text": "Claim: id",
      "url": "https://www.w3.org/TR/vc-data-model-2.0/#sd-jwt-claim-bdqQsIhoaqd0G16vD6iwVE5RcIS3BEz47wJfZwVy6ug"
    }
  },
  "#sd-jwt-claim-beRQh77-pkUrYW9ps0ammLC5LDutf1nO61Nwg7foERM": {
    "current": {
      "number": "",
      "spec": "Verifiable Credentials Data Model v2.0",
      "text": "Claim: type",
      "url": "https://w3c.github.io/vc-data-model/#sd-jwt-claim-beRQh77-pkUrYW9ps0ammLC5LDutf1nO61Nwg7foERM"
    }
  },
  "#sd-jwt-claim-cb1q3QUfyjXpPCdp8PdW-gb09V_nSjw2EApTlyD2-t8": {
    "current": {
      "number": "",
      "spec": "Verifiable Credentials Data Model v2.0",
      "text": "Claim: id",
      "url": "https://w3c.github.io/vc-data-model/#sd-jwt-claim-cb1q3QUfyjXpPCdp8PdW-gb09V_nSjw2EApTlyD2-t8"
    }
  },
  "#sd-jwt-claim-doZ4wtQ7DiuKsquPlBMEOgTtqXxqgSg4KYU1hj868Fc": {
    "current": {
      "number": "",
      "spec": "Verifiable Credentials Data Model v2.0",
      "text": "Claim: type",
      "url": "https://w3c.github.io/vc-data-model/#sd-jwt-claim-doZ4wtQ7DiuKsquPlBMEOgTtqXxqgSg4KYU1hj868Fc"
    }
  },
  "#sd-jwt-claim-duhLMHjjksfqcQkRzWPyTGBPV8HqGhv4V8tC7_dshrk": {
    "snapshot": {
      "number": "",
      "spec": "Verifiable Credentials Data Model v2.0",
      "text": "Claim: type",
      "url": "https://www.w3.org/TR/vc-data-model-2.0/#sd-jwt-claim-duhLMHjjksfqcQkRzWPyTGBPV8HqGhv4V8tC7_dshrk"
    }
  },
  "#sd-jwt-claim-fEv-2cdhWK53O87pJLuayW5oMjz7qvUGinNNhW1m00A": {
    "current": {
      "number": "",
      "spec": "Verifiable Credentials Data Model v2.0",
      "text": "Claim: id",
      "url": "https://w3c.github.io/vc-data-model/#sd-jwt-claim-fEv-2cdhWK53O87pJLuayW5oMjz7qvUGinNNhW1m00A"
    }
  },
  "#sd-jwt-claim-hSDaFFj1JB_1PJE6_1BaNXuLGNsTTWwVAlvjGjewGzU": {
    "current": {
      "number": "",
      "spec": "Verifiable Credentials Data Model v2.0",
      "text": "Claim: type",
      "url": "https://w3c.github.io/vc-data-model/#sd-jwt-claim-hSDaFFj1JB_1PJE6_1BaNXuLGNsTTWwVAlvjGjewGzU"
    }
  },
  "#sd-jwt-claim-iBQcPcMGAVU5K7sgMV_1cDPobqlaocunZSNGEzq6GAA": {
    "current": {
      "number": "",
      "spec": "Verifiable Credentials Data Model v2.0",
      "text": "Claim: type",
      "url": "https://w3c.github.io/vc-data-model/#sd-jwt-claim-iBQcPcMGAVU5K7sgMV_1cDPobqlaocunZSNGEzq6GAA"
    }
  },
  "#sd-jwt-claim-iHqQyeFM6HILcX8Qu44OkSPDqY9KlKqYoaJVTFzUDRo": {
    "snapshot": {
      "number": "",
      "spec": "Verifiable Credentials Data Model v2.0",
      "text": "Claim: id",
      "url": "https://www.w3.org/TR/vc-data-model-2.0/#sd-jwt-claim-iHqQyeFM6HILcX8Qu44OkSPDqY9KlKqYoaJVTFzUDRo"
    }
  },
  "#sd-jwt-claim-j07RZH6vGuiIrhCNS3pvRbcWfBQEBB4dG8ZGbHaRP18": {
    "current": {
      "number": "",
      "spec": "Verifiable Credentials Data Model v2.0",
      "text": "Claim: id",
      "url": "https://w3c.github.io/vc-data-model/#sd-jwt-claim-j07RZH6vGuiIrhCNS3pvRbcWfBQEBB4dG8ZGbHaRP18"
    }
  },
  "#sd-jwt-claim-jBr6C36Y6vq93pQYZK9n-zkQc4BY-AMCg4tWwBgf95Y": {
    "snapshot": {
      "number": "",
      "spec": "Verifiable Credentials Data Model v2.0",
      "text": "Claim: id",
      "url": "https://www.w3.org/TR/vc-data-model-2.0/#sd-jwt-claim-jBr6C36Y6vq93pQYZK9n-zkQc4BY-AMCg4tWwBgf95Y"
    }
  },
  "#sd-jwt-claim-kH03CbbQDQQq9fNq6I54Uvok3VrC-cUWFaFuROV7Tm0": {
    "snapshot": {
      "number": "",
      "spec": "Verifiable Credentials Data Model v2.0",
      "text": "Claim: type",
      "url": "https://www.w3.org/TR/vc-data-model-2.0/#sd-jwt-claim-kH03CbbQDQQq9fNq6I54Uvok3VrC-cUWFaFuROV7Tm0"
    }
  },
  "#sd-jwt-claim-kVJxm7RZGFzejiuf9KIP2loTD97pcQ22-tIcKDqvdSU": {
    "current": {
      "number": "",
      "spec": "Verifiable Credentials Data Model v2.0",
      "text": "Claim: type",
      "url": "https://w3c.github.io/vc-data-model/#sd-jwt-claim-kVJxm7RZGFzejiuf9KIP2loTD97pcQ22-tIcKDqvdSU"
    }
  },
  "#sd-jwt-claim-oA-sxYDs5VpN2RjzBtKBP2QXewGGPsVk8f2BfqOYnpc": {
    "current": {
      "number": "",
      "spec": "Verifiable Credentials Data Model v2.0",
      "text": "Claim: id",
      "url": "https://w3c.github.io/vc-data-model/#sd-jwt-claim-oA-sxYDs5VpN2RjzBtKBP2QXewGGPsVk8f2BfqOYnpc"
    }
  },
  "#sd-jwt-claim-pQUdeid9JuxVmBMFEl1C2C4Nz__ccWZDUBSzcihS2Qo": {
    "snapshot": {
      "number": "",
      "spec": "Verifiable Credentials Data Model v2.0",
      "text": "Claim: id",
      "url": "https://www.w3.org/TR/vc-data-model-2.0/#sd-jwt-claim-pQUdeid9JuxVmBMFEl1C2C4Nz__ccWZDUBSzcihS2Qo"
    }
  },
  "#sd-jwt-claim-q1ZlI2SupPvKhCdSyJ1bIogy0OzB0rxwLtduD-dcxKA": {
    "current": {
      "number": "",
      "spec": "Verifiable Credentials Data Model v2.0",
      "text": "Claim: id",
      "url": "https://w3c.github.io/vc-data-model/#sd-jwt-claim-q1ZlI2SupPvKhCdSyJ1bIogy0OzB0rxwLtduD-dcxKA"
    }
  },
  "#sd-jwt-claim-qwK7T9-kG8Cv2NpNEAlFlProDMcWIhN220j6hoEDHh4": {
    "current": {
      "number": "",
      "spec": "Verifiable Credentials Data Model v2.0",
      "text": "Claim: id",
      "url": "https://w3c.github.io/vc-data-model/#sd-jwt-claim-qwK7T9-kG8Cv2NpNEAlFlProDMcWIhN220j6hoEDHh4"
    }
  },
  "#sd-jwt-claim-rLrZkMnPG-t6jJFciz_5v5-doPanhaqXesJhayNEVYI": {
    "current": {
      "number": "",
      "spec": "Verifiable Credentials Data Model v2.0",
      "text": "Claim: id",
      "url": "https://w3c.github.io/vc-data-model/#sd-jwt-claim-rLrZkMnPG-t6jJFciz_5v5-doPanhaqXesJhayNEVYI"
    }
  },
  "#sd-jwt-claim-rLrciyzPYuA1CKZv7nLRlQ0nRupyCYELJcRgyMawV4I": {
    "current": {
      "number": "",
      "spec": "Verifiable Credentials Data Model v2.0",
      "text": "Claim: id",
      "url": "https://w3c.github.io/vc-data-model/#sd-jwt-claim-rLrciyzPYuA1CKZv7nLRlQ0nRupyCYELJcRgyMawV4I"
    }
  },
  "#sd-jwt-claim-rdoX6X79NXxbY6i9fAdQnjjiwa11UwV8qsA5wWAhCEA": {
    "snapshot": {
      "number": "",
      "spec": "Verifiable Credentials Data Model v2.0",
      "text": "Claim: id",
      "url": "https://www.w3.org/TR/vc-data-model-2.0/#sd-jwt-claim-rdoX6X79NXxbY6i9fAdQnjjiwa11UwV8qsA5wWAhCEA"
    }
  },
  "#sd-jwt-claim-rrfnwm6Rd-FSNjzJkESNpE3NXXK0Wco0_0rZdbY_Vxo": {
    "snapshot": {
      "number": "",
      "spec": "Verifiable Credentials Data Model v2.0",
      "text": "Claim: id",
      "url": "https://www.w3.org/TR/vc-data-model-2.0/#sd-jwt-claim-rrfnwm6Rd-FSNjzJkESNpE3NXXK0Wco0_0rZdbY_Vxo"
    }
  },
  "#sd-jwt-claim-sCINApW-YRCYHAxI-6ADTw-9sbwmqKHgwd3G-Sp2i0A": {
    "snapshot": {
      "number": "",
      "spec": "Verifiable Credentials Data Model v2.0",
      "text": "Claim: type",
      "url": "https://www.w3.org/TR/vc-data-model-2.0/#sd-jwt-claim-sCINApW-YRCYHAxI-6ADTw-9sbwmqKHgwd3G-Sp2i0A"
    }
  },
  "#sd-jwt-claim-v8H5knvGctAa8P0-nwfzfDeIIZgd6L6WoNSvlTu8iYo": {
    "current": {
      "number": "",
      "spec": "Verifiable Credentials Data Model v2.0",
      "text": "Claim: type",
      "url": "https://w3c.github.io/vc-data-model/#sd-jwt-claim-v8H5knvGctAa8P0-nwfzfDeIIZgd6L6WoNSvlTu8iYo"
    }
  },
  "#sd-jwt-claim-vPw6LSrrQmTfyf9YTvMdnXLhUR9ExVHDNVBL4AwVUBA": {
    "current": {
      "number": "",
      "spec": "Verifiable Credentials Data Model v2.0",
      "text": "Claim: id",
      "url": "https://w3c.github.io/vc-data-model/#sd-jwt-claim-vPw6LSrrQmTfyf9YTvMdnXLhUR9ExVHDNVBL4AwVUBA"
    }
  },
  "#sd-jwt-claim-wjHYxqi5NiKX1PivbynUepJz94e00C2Wg0CV9KpDa3U": {
    "current": {
      "number": "",
      "spec": "Verifiable Credentials Data Model v2.0",
      "text": "Claim: id",
      "url": "https://w3c.github.io/vc-data-model/#sd-jwt-claim-wjHYxqi5NiKX1PivbynUepJz94e00C2Wg0CV9KpDa3U"
    }
  },
  "#sd-jwt-claim-wnWN0qHn-kOxxGHvcoJG4J2s-hJTynAAgegUAo34ysk": {
    "snapshot": {
      "number": "",
      "spec": "Verifiable Credentials Data Model v2.0",
      "text": "Claim: id",
      "url": "https://www.w3.org/TR/vc-data-model-2.0/#sd-jwt-claim-wnWN0qHn-kOxxGHvcoJG4J2s-hJTynAAgegUAo34ysk"
    }
  },
  "#sd-jwt-claim-y1Y1cl6jig4Th3L0zcr74uPImgEgiuKBawKu_JcTu5g": {
    "snapshot": {
      "number": "",
      "spec": "Verifiable Credentials Data Model v2.0",
      "text": "Claim: type",
      "url": "https://www.w3.org/TR/vc-data-model-2.0/#sd-jwt-claim-y1Y1cl6jig4Th3L0zcr74uPImgEgiuKBawKu_JcTu5g"
    }
  },
  "#sd-jwt-claim-zoVT3II8c4V3dcjRXqJT7XcvLKJOAf2WV08GEhB8hjo": {
    "current": {
      "number": "",
      "spec": "Verifiable Credentials Data Model v2.0",
      "text": "Claim: type",
      "url": "https://w3c.github.io/vc-data-model/#sd-jwt-claim-zoVT3II8c4V3dcjRXqJT7XcvLKJOAf2WV08GEhB8hjo"
    }
  },
  "#securing-mechanism-specifications": {
    "current": {
      "number": "5.13",
      "spec": "Verifiable Credentials Data Model v2.0",
      "text": "Securing Mechanism Specifications",
      "url": "https://w3c.github.io/vc-data-model/#securing-mechanism-specifications"
    },
    "snapshot": {
      "number": "5.13",
      "spec": "Verifiable Credentials Data Model v2.0",
      "text": "Securing Mechanism Specifications",
      "url": "https://www.w3.org/TR/vc-data-model-2.0/#securing-mechanism-specifications"
    }
  },
  "#securing-mechanisms": {
    "current": {
      "number": "4.12",
      "spec": "Verifiable Credentials Data Model v2.0",
      "text": "Securing Mechanisms",
      "url": "https://w3c.github.io/vc-data-model/#securing-mechanisms"
    },
    "snapshot": {
      "number": "4.12",
      "spec": "Verifiable Credentials Data Model v2.0",
      "text": "Securing Mechanisms",
      "url": "https://www.w3.org/TR/vc-data-model-2.0/#securing-mechanisms"
    }
  },
  "#security-considerations": {
    "current": {
      "number": "9",
      "spec": "Verifiable Credentials Data Model v2.0",
      "text": "Security Considerations",
      "url": "https://w3c.github.io/vc-data-model/#security-considerations"
    },
    "snapshot": {
      "number": "9",
      "spec": "Verifiable Credentials Data Model v2.0",
      "text": "Security Considerations",
      "url": "https://www.w3.org/TR/vc-data-model-2.0/#security-considerations"
    }
  },
  "#semantic-interoperability": {
    "current": {
      "number": "",
      "spec": "Verifiable Credentials Data Model v2.0",
      "text": "Semantic Interoperability",
      "url": "https://w3c.github.io/vc-data-model/#semantic-interoperability"
    },
    "snapshot": {
      "number": "",
      "spec": "Verifiable Credentials Data Model v2.0",
      "text": "Semantic Interoperability",
      "url": "https://www.w3.org/TR/vc-data-model-2.0/#semantic-interoperability"
    }
  },
  "#sharing-information-with-the-wrong-party": {
    "current": {
      "number": "8.16",
      "spec": "Verifiable Credentials Data Model v2.0",
      "text": "Sharing Information with the Wrong Party",
      "url": "https://w3c.github.io/vc-data-model/#sharing-information-with-the-wrong-party"
    },
    "snapshot": {
      "number": "8.16",
      "spec": "Verifiable Credentials Data Model v2.0",
      "text": "Sharing Information with the Wrong Party",
      "url": "https://www.w3.org/TR/vc-data-model-2.0/#sharing-information-with-the-wrong-party"
    }
  },
  "#signature-based-correlation": {
    "current": {
      "number": "8.5",
      "spec": "Verifiable Credentials Data Model v2.0",
      "text": "Signature-Based Correlation",
      "url": "https://w3c.github.io/vc-data-model/#signature-based-correlation"
    },
    "snapshot": {
      "number": "8.5",
      "spec": "Verifiable Credentials Data Model v2.0",
      "text": "Signature-Based Correlation",
      "url": "https://www.w3.org/TR/vc-data-model-2.0/#signature-based-correlation"
    }
  },
  "#software-trust-boundaries": {
    "current": {
      "number": "8.2",
      "spec": "Verifiable Credentials Data Model v2.0",
      "text": "Software Trust Boundaries",
      "url": "https://w3c.github.io/vc-data-model/#software-trust-boundaries"
    },
    "snapshot": {
      "number": "8.2",
      "spec": "Verifiable Credentials Data Model v2.0",
      "text": "Software Trust Boundaries",
      "url": "https://www.w3.org/TR/vc-data-model-2.0/#software-trust-boundaries"
    }
  },
  "#spectrum-of-privacy": {
    "current": {
      "number": "8.1",
      "spec": "Verifiable Credentials Data Model v2.0",
      "text": "Spectrum of Privacy",
      "url": "https://w3c.github.io/vc-data-model/#spectrum-of-privacy"
    },
    "snapshot": {
      "number": "8.1",
      "spec": "Verifiable Credentials Data Model v2.0",
      "text": "Spectrum of Privacy",
      "url": "https://www.w3.org/TR/vc-data-model-2.0/#spectrum-of-privacy"
    }
  },
  "#spoofing-attack": {
    "current": {
      "number": "9.5.3",
      "spec": "Verifiable Credentials Data Model v2.0",
      "text": "Spoofing Attack",
      "url": "https://w3c.github.io/vc-data-model/#spoofing-attack"
    },
    "snapshot": {
      "number": "9.5.3",
      "spec": "Verifiable Credentials Data Model v2.0",
      "text": "Spoofing Attack",
      "url": "https://www.w3.org/TR/vc-data-model-2.0/#spoofing-attack"
    }
  },
  "#status": {
    "current": {
      "number": "4.10",
      "spec": "Verifiable Credentials Data Model v2.0",
      "text": "Status",
      "url": "https://w3c.github.io/vc-data-model/#status"
    },
    "snapshot": {
      "number": "4.10",
      "spec": "Verifiable Credentials Data Model v2.0",
      "text": "Status",
      "url": "https://www.w3.org/TR/vc-data-model-2.0/#status"
    }
  },
  "#status-0": {
    "current": {
      "number": "A.8",
      "spec": "Verifiable Credentials Data Model v2.0",
      "text": "Status",
      "url": "https://w3c.github.io/vc-data-model/#status-0"
    },
    "snapshot": {
      "number": "A.8",
      "spec": "Verifiable Credentials Data Model v2.0",
      "text": "Status",
      "url": "https://www.w3.org/TR/vc-data-model-2.0/#status-0"
    }
  },
  "#storage-providers-and-data-mining": {
    "current": {
      "number": "8.12",
      "spec": "Verifiable Credentials Data Model v2.0",
      "text": "Storage Providers and Data Mining",
      "url": "https://w3c.github.io/vc-data-model/#storage-providers-and-data-mining"
    },
    "snapshot": {
      "number": "8.12",
      "spec": "Verifiable Credentials Data Model v2.0",
      "text": "Storage Providers and Data Mining",
      "url": "https://www.w3.org/TR/vc-data-model-2.0/#storage-providers-and-data-mining"
    }
  },
  "#syntaxes": {
    "current": {
      "number": "6",
      "spec": "Verifiable Credentials Data Model v2.0",
      "text": "Syntaxes",
      "url": "https://w3c.github.io/vc-data-model/#syntaxes"
    },
    "snapshot": {
      "number": "6",
      "spec": "Verifiable Credentials Data Model v2.0",
      "text": "Syntaxes",
      "url": "https://www.w3.org/TR/vc-data-model-2.0/#syntaxes"
    }
  },
  "#terminology": {
    "current": {
      "number": "2",
      "spec": "Verifiable Credentials Data Model v2.0",
      "text": "Terminology",
      "url": "https://w3c.github.io/vc-data-model/#terminology"
    },
    "snapshot": {
      "number": "2",
      "spec": "Verifiable Credentials Data Model v2.0",
      "text": "Terminology",
      "url": "https://www.w3.org/TR/vc-data-model-2.0/#terminology"
    }
  },
  "#terms-of-use": {
    "current": {
      "number": "5.5",
      "spec": "Verifiable Credentials Data Model v2.0",
      "text": "Terms of Use",
      "url": "https://w3c.github.io/vc-data-model/#terms-of-use"
    },
    "snapshot": {
      "number": "5.5",
      "spec": "Verifiable Credentials Data Model v2.0",
      "text": "Terms of Use",
      "url": "https://www.w3.org/TR/vc-data-model-2.0/#terms-of-use"
    }
  },
  "#the-principle-of-data-minimization": {
    "current": {
      "number": "8.9",
      "spec": "Verifiable Credentials Data Model v2.0",
      "text": "The Principle of Data Minimization",
      "url": "https://w3c.github.io/vc-data-model/#the-principle-of-data-minimization"
    },
    "snapshot": {
      "number": "8.9",
      "spec": "Verifiable Credentials Data Model v2.0",
      "text": "The Principle of Data Minimization",
      "url": "https://www.w3.org/TR/vc-data-model-2.0/#the-principle-of-data-minimization"
    }
  },
  "#the-sristring-datatype": {
    "current": {
      "number": "B.3.1",
      "spec": "Verifiable Credentials Data Model v2.0",
      "text": "The sriString Datatype",
      "url": "https://w3c.github.io/vc-data-model/#the-sristring-datatype"
    },
    "snapshot": {
      "number": "B.3.1",
      "spec": "Verifiable Credentials Data Model v2.0",
      "text": "The sriString Datatype",
      "url": "https://www.w3.org/TR/vc-data-model-2.0/#the-sristring-datatype"
    }
  },
  "#title": {
    "current": {
      "number": "",
      "spec": "Verifiable Credentials Data Model v2.0",
      "text": "Verifiable Credentials Data Model v2.0",
      "url": "https://w3c.github.io/vc-data-model/#title"
    },
    "snapshot": {
      "number": "",
      "spec": "Verifiable Credentials Data Model v2.0",
      "text": "Verifiable Credentials Data Model v2.0",
      "url": "https://www.w3.org/TR/vc-data-model-2.0/#title"
    }
  },
  "#toc": {
    "current": {
      "number": "",
      "spec": "Verifiable Credentials Data Model v2.0",
      "text": "Table of Contents",
      "url": "https://w3c.github.io/vc-data-model/#toc"
    },
    "snapshot": {
      "number": "",
      "spec": "Verifiable Credentials Data Model v2.0",
      "text": "Table of Contents",
      "url": "https://www.w3.org/TR/vc-data-model-2.0/#toc"
    }
  },
  "#trust-model": {
    "current": {
      "number": "5.1",
      "spec": "Verifiable Credentials Data Model v2.0",
      "text": "Trust Model",
      "url": "https://w3c.github.io/vc-data-model/#trust-model"
    },
    "snapshot": {
      "number": "5.1",
      "spec": "Verifiable Credentials Data Model v2.0",
      "text": "Trust Model",
      "url": "https://www.w3.org/TR/vc-data-model-2.0/#trust-model"
    }
  },
  "#type-specific-credential-processing": {
    "current": {
      "number": "6.3",
      "spec": "Verifiable Credentials Data Model v2.0",
      "text": "Type-Specific Credential Processing",
      "url": "https://w3c.github.io/vc-data-model/#type-specific-credential-processing"
    },
    "snapshot": {
      "number": "6.3",
      "spec": "Verifiable Credentials Data Model v2.0",
      "text": "Type-Specific Credential Processing",
      "url": "https://www.w3.org/TR/vc-data-model-2.0/#type-specific-credential-processing"
    }
  },
  "#types": {
    "current": {
      "number": "4.5",
      "spec": "Verifiable Credentials Data Model v2.0",
      "text": "Types",
      "url": "https://w3c.github.io/vc-data-model/#types"
    },
    "snapshot": {
      "number": "4.5",
      "spec": "Verifiable Credentials Data Model v2.0",
      "text": "Types",
      "url": "https://www.w3.org/TR/vc-data-model-2.0/#types"
    }
  },
  "#unauthorized-use": {
    "current": {
      "number": "9.9.1",
      "spec": "Verifiable Credentials Data Model v2.0",
      "text": "Unauthorized Use",
      "url": "https://w3c.github.io/vc-data-model/#unauthorized-use"
    },
    "snapshot": {
      "number": "9.9.1",
      "spec": "Verifiable Credentials Data Model v2.0",
      "text": "Unauthorized Use",
      "url": "https://www.w3.org/TR/vc-data-model-2.0/#unauthorized-use"
    }
  },
  "#unsigned-claims": {
    "current": {
      "number": "9.4",
      "spec": "Verifiable Credentials Data Model v2.0",
      "text": "Unsigned Claims",
      "url": "https://w3c.github.io/vc-data-model/#unsigned-claims"
    },
    "snapshot": {
      "number": "9.4",
      "spec": "Verifiable Credentials Data Model v2.0",
      "text": "Unsigned Claims",
      "url": "https://www.w3.org/TR/vc-data-model-2.0/#unsigned-claims"
    }
  },
  "#validation": {
    "current": {
      "number": "A",
      "spec": "Verifiable Credentials Data Model v2.0",
      "text": "Validation",
      "url": "https://w3c.github.io/vc-data-model/#validation"
    },
    "snapshot": {
      "number": "A",
      "spec": "Verifiable Credentials Data Model v2.0",
      "text": "Validation",
      "url": "https://www.w3.org/TR/vc-data-model-2.0/#validation"
    }
  },
  "#validity-period": {
    "current": {
      "number": "4.9",
      "spec": "Verifiable Credentials Data Model v2.0",
      "text": "Validity Period",
      "url": "https://w3c.github.io/vc-data-model/#validity-period"
    },
    "snapshot": {
      "number": "4.9",
      "spec": "Verifiable Credentials Data Model v2.0",
      "text": "Validity Period",
      "url": "https://www.w3.org/TR/vc-data-model-2.0/#validity-period"
    }
  },
  "#validity-periods": {
    "current": {
      "number": "A.7",
      "spec": "Verifiable Credentials Data Model v2.0",
      "text": "Validity Periods",
      "url": "https://w3c.github.io/vc-data-model/#validity-periods"
    },
    "snapshot": {
      "number": "A.7",
      "spec": "Verifiable Credentials Data Model v2.0",
      "text": "Validity Periods",
      "url": "https://www.w3.org/TR/vc-data-model-2.0/#validity-periods"
    }
  },
  "#vc-ld-media-type": {
    "current": {
      "number": "C.1",
      "spec": "Verifiable Credentials Data Model v2.0",
      "text": "application/vc",
      "url": "https://w3c.github.io/vc-data-model/#vc-ld-media-type"
    },
    "snapshot": {
      "number": "C.1",
      "spec": "Verifiable Credentials Data Model v2.0",
      "text": "application/vc",
      "url": "https://www.w3.org/TR/vc-data-model-2.0/#vc-ld-media-type"
    }
  },
  "#verifiable-credential-graphs": {
    "current": {
      "number": "5.12",
      "spec": "Verifiable Credentials Data Model v2.0",
      "text": "Verifiable Credential Graphs",
      "url": "https://w3c.github.io/vc-data-model/#verifiable-credential-graphs"
    },
    "snapshot": {
      "number": "5.12",
      "spec": "Verifiable Credentials Data Model v2.0",
      "text": "Verifiable Credential Graphs",
      "url": "https://www.w3.org/TR/vc-data-model-2.0/#verifiable-credential-graphs"
    }
  },
  "#verifiable-credentials": {
    "current": {
      "number": "4.2",
      "spec": "Verifiable Credentials Data Model v2.0",
      "text": "Verifiable Credentials",
      "url": "https://w3c.github.io/vc-data-model/#verifiable-credentials"
    },
    "snapshot": {
      "number": "4.2",
      "spec": "Verifiable Credentials Data Model v2.0",
      "text": "Verifiable Credentials",
      "url": "https://www.w3.org/TR/vc-data-model-2.0/#verifiable-credentials"
    }
  },
  "#verifiable-presentations": {
    "current": {
      "number": "4.13",
      "spec": "Verifiable Credentials Data Model v2.0",
      "text": "Verifiable Presentations",
      "url": "https://w3c.github.io/vc-data-model/#verifiable-presentations"
    },
    "snapshot": {
      "number": "4.13",
      "spec": "Verifiable Credentials Data Model v2.0",
      "text": "Verifiable Presentations",
      "url": "https://www.w3.org/TR/vc-data-model-2.0/#verifiable-presentations"
    }
  },
  "#verification": {
    "current": {
      "number": "7.1",
      "spec": "Verifiable Credentials Data Model v2.0",
      "text": "Verification",
      "url": "https://w3c.github.io/vc-data-model/#verification"
    },
    "snapshot": {
      "number": "7.1",
      "spec": "Verifiable Credentials Data Model v2.0",
      "text": "Verification",
      "url": "https://www.w3.org/TR/vc-data-model-2.0/#verification"
    }
  },
  "#vocabularies": {
    "current": {
      "number": "B.2",
      "spec": "Verifiable Credentials Data Model v2.0",
      "text": "Vocabularies",
      "url": "https://w3c.github.io/vc-data-model/#vocabularies"
    },
    "snapshot": {
      "number": "B.2",
      "spec": "Verifiable Credentials Data Model v2.0",
      "text": "Vocabularies",
      "url": "https://www.w3.org/TR/vc-data-model-2.0/#vocabularies"
    }
  },
  "#vp-ld-media-type": {
    "current": {
      "number": "C.2",
      "spec": "Verifiable Credentials Data Model v2.0",
      "text": "application/vp",
      "url": "https://w3c.github.io/vc-data-model/#vp-ld-media-type"
    },
    "snapshot": {
      "number": "C.2",
      "spec": "Verifiable Credentials Data Model v2.0",
      "text": "application/vp",
      "url": "https://www.w3.org/TR/vc-data-model-2.0/#vp-ld-media-type"
    }
  },
  "#what-is-a-verifiable-credential": {
    "current": {
      "number": "1.1",
      "spec": "Verifiable Credentials Data Model v2.0",
      "text": "What is a Verifiable Credential?",
      "url": "https://w3c.github.io/vc-data-model/#what-is-a-verifiable-credential"
    },
    "snapshot": {
      "number": "1.1",
      "spec": "Verifiable Credentials Data Model v2.0",
      "text": "What is a Verifiable Credential?",
      "url": "https://www.w3.org/TR/vc-data-model-2.0/#what-is-a-verifiable-credential"
    }
  },
  "#zero-knowledge-proofs": {
    "current": {
      "number": "5.7",
      "spec": "Verifiable Credentials Data Model v2.0",
      "text": "Zero-Knowledge Proofs",
      "url": "https://w3c.github.io/vc-data-model/#zero-knowledge-proofs"
    },
    "snapshot": {
      "number": "5.7",
      "spec": "Verifiable Credentials Data Model v2.0",
      "text": "Zero-Knowledge Proofs",
      "url": "https://www.w3.org/TR/vc-data-model-2.0/#zero-knowledge-proofs"
    }
  }
}