{
  "#a-1-normative-references": {
    "current": {
      "number": "A.1",
      "spec": "Verifiable Credential Rendering Methods v1.0",
      "text": "Normative references",
      "url": "https://w3c.github.io/vc-render-method/#normative-references"
    },
    "snapshot": {
      "number": "A.1",
      "spec": "Verifiable Credential Rendering Methods v1.0",
      "text": "Normative references",
      "url": "https://www.w3.org/TR/vc-render-method/#normative-references"
    }
  },
  "#a-references": {
    "current": {
      "number": "A",
      "spec": "Verifiable Credential Rendering Methods v1.0",
      "text": "References",
      "url": "https://w3c.github.io/vc-render-method/#references"
    },
    "snapshot": {
      "number": "A",
      "spec": "Verifiable Credential Rendering Methods v1.0",
      "text": "References",
      "url": "https://www.w3.org/TR/vc-render-method/#references"
    }
  },
  "#action-api": {
    "current": {
      "number": "2.3.1",
      "spec": "Verifiable Credential Rendering Methods v1.0",
      "text": "Action API",
      "url": "https://w3c.github.io/vc-render-method/#action-api"
    },
    "snapshot": {
      "number": "2.3.1",
      "spec": "Verifiable Credential Rendering Methods v1.0",
      "text": "Action API",
      "url": "https://www.w3.org/TR/vc-render-method/#action-api"
    }
  },
  "#algorithms": {
    "current": {
      "number": "3",
      "spec": "Verifiable Credential Rendering Methods v1.0",
      "text": "Algorithms",
      "url": "https://w3c.github.io/vc-render-method/#algorithms"
    },
    "snapshot": {
      "number": "3",
      "spec": "Verifiable Credential Rendering Methods v1.0",
      "text": "Algorithms",
      "url": "https://www.w3.org/TR/vc-render-method/#algorithms"
    }
  },
  "#conformance": {
    "current": {
      "number": "1.2",
      "spec": "Verifiable Credential Rendering Methods v1.0",
      "text": "Conformance",
      "url": "https://w3c.github.io/vc-render-method/#conformance"
    },
    "snapshot": {
      "number": "1.2",
      "spec": "Verifiable Credential Rendering Methods v1.0",
      "text": "Conformance",
      "url": "https://www.w3.org/TR/vc-render-method/#conformance"
    }
  },
  "#data-model": {
    "current": {
      "number": "2",
      "spec": "Verifiable Credential Rendering Methods v1.0",
      "text": "Data Model",
      "url": "https://w3c.github.io/vc-render-method/#data-model"
    },
    "snapshot": {
      "number": "2",
      "spec": "Verifiable Credential Rendering Methods v1.0",
      "text": "Data Model",
      "url": "https://www.w3.org/TR/vc-render-method/#data-model"
    }
  },
  "#frame-to-host-actions": {
    "current": {
      "number": "2.3.1.2",
      "spec": "Verifiable Credential Rendering Methods v1.0",
      "text": "Frame-to-Host Actions",
      "url": "https://w3c.github.io/vc-render-method/#frame-to-host-actions"
    },
    "snapshot": {
      "number": "2.3.1.2",
      "spec": "Verifiable Credential Rendering Methods v1.0",
      "text": "Frame-to-Host Actions",
      "url": "https://www.w3.org/TR/vc-render-method/#frame-to-host-actions"
    }
  },
  "#host-to-frame-actions": {
    "current": {
      "number": "2.3.1.1",
      "spec": "Verifiable Credential Rendering Methods v1.0",
      "text": "Host-to-Frame Actions",
      "url": "https://w3c.github.io/vc-render-method/#host-to-frame-actions"
    },
    "snapshot": {
      "number": "2.3.1.1",
      "spec": "Verifiable Credential Rendering Methods v1.0",
      "text": "Host-to-Frame Actions",
      "url": "https://www.w3.org/TR/vc-render-method/#host-to-frame-actions"
    }
  },
  "#internationalization-considerations": {
    "current": {
      "number": "6",
      "spec": "Verifiable Credential Rendering Methods v1.0",
      "text": "Internationalization Considerations",
      "url": "https://w3c.github.io/vc-render-method/#internationalization-considerations"
    },
    "snapshot": {
      "number": "6",
      "spec": "Verifiable Credential Rendering Methods v1.0",
      "text": "Internationalization Considerations",
      "url": "https://www.w3.org/TR/vc-render-method/#internationalization-considerations"
    }
  },
  "#introduction": {
    "current": {
      "number": "1",
      "spec": "Verifiable Credential Rendering Methods v1.0",
      "text": "Introduction",
      "url": "https://w3c.github.io/vc-render-method/#introduction"
    },
    "snapshot": {
      "number": "1",
      "spec": "Verifiable Credential Rendering Methods v1.0",
      "text": "Introduction",
      "url": "https://www.w3.org/TR/vc-render-method/#introduction"
    }
  },
  "#normative-references": {
    "current": {
      "number": "A.1",
      "spec": "Verifiable Credential Rendering Methods v1.0",
      "text": "Normative references",
      "url": "https://w3c.github.io/vc-render-method/#normative-references"
    },
    "snapshot": {
      "number": "A.1",
      "spec": "Verifiable Credential Rendering Methods v1.0",
      "text": "Normative references",
      "url": "https://www.w3.org/TR/vc-render-method/#normative-references"
    }
  },
  "#openattestationembeddedrenderer": {
    "current": {
      "number": "2.3",
      "spec": "Verifiable Credential Rendering Methods v1.0",
      "text": "OpenAttestationEmbeddedRenderer",
      "url": "https://w3c.github.io/vc-render-method/#openattestationembeddedrenderer"
    },
    "snapshot": {
      "number": "2.3",
      "spec": "Verifiable Credential Rendering Methods v1.0",
      "text": "OpenAttestationEmbeddedRenderer",
      "url": "https://www.w3.org/TR/vc-render-method/#openattestationembeddedrenderer"
    }
  },
  "#privacy-considerations": {
    "current": {
      "number": "5",
      "spec": "Verifiable Credential Rendering Methods v1.0",
      "text": "Privacy Considerations",
      "url": "https://w3c.github.io/vc-render-method/#privacy-considerations"
    },
    "snapshot": {
      "number": "5",
      "spec": "Verifiable Credential Rendering Methods v1.0",
      "text": "Privacy Considerations",
      "url": "https://www.w3.org/TR/vc-render-method/#privacy-considerations"
    }
  },
  "#references": {
    "current": {
      "number": "A",
      "spec": "Verifiable Credential Rendering Methods v1.0",
      "text": "References",
      "url": "https://w3c.github.io/vc-render-method/#references"
    },
    "snapshot": {
      "number": "A",
      "spec": "Verifiable Credential Rendering Methods v1.0",
      "text": "References",
      "url": "https://www.w3.org/TR/vc-render-method/#references"
    }
  },
  "#render-templaterendermethod": {
    "current": {
      "number": "3.1",
      "spec": "Verifiable Credential Rendering Methods v1.0",
      "text": "Render (TemplateRenderMethod)",
      "url": "https://w3c.github.io/vc-render-method/#render-templaterendermethod"
    },
    "snapshot": {
      "number": "3.1",
      "spec": "Verifiable Credential Rendering Methods v1.0",
      "text": "Render (TemplateRenderMethod)",
      "url": "https://www.w3.org/TR/vc-render-method/#render-templaterendermethod"
    }
  },
  "#security-considerations": {
    "current": {
      "number": "4",
      "spec": "Verifiable Credential Rendering Methods v1.0",
      "text": "Security Considerations",
      "url": "https://w3c.github.io/vc-render-method/#security-considerations"
    },
    "snapshot": {
      "number": "4",
      "spec": "Verifiable Credential Rendering Methods v1.0",
      "text": "Security Considerations",
      "url": "https://www.w3.org/TR/vc-render-method/#security-considerations"
    }
  },
  "#table-of-contents": {
    "current": {
      "number": "",
      "spec": "Verifiable Credential Rendering Methods v1.0",
      "text": "Table of Contents",
      "url": "https://w3c.github.io/vc-render-method/#toc"
    },
    "snapshot": {
      "number": "",
      "spec": "Verifiable Credential Rendering Methods v1.0",
      "text": "Table of Contents",
      "url": "https://www.w3.org/TR/vc-render-method/#toc"
    }
  },
  "#templaterendermethod": {
    "current": {
      "number": "2.2",
      "spec": "Verifiable Credential Rendering Methods v1.0",
      "text": "TemplateRenderMethod",
      "url": "https://w3c.github.io/vc-render-method/#templaterendermethod"
    },
    "snapshot": {
      "number": "2.2",
      "spec": "Verifiable Credential Rendering Methods v1.0",
      "text": "TemplateRenderMethod",
      "url": "https://www.w3.org/TR/vc-render-method/#templaterendermethod"
    }
  },
  "#terminology": {
    "current": {
      "number": "1.1",
      "spec": "Verifiable Credential Rendering Methods v1.0",
      "text": "Terminology",
      "url": "https://w3c.github.io/vc-render-method/#terminology"
    },
    "snapshot": {
      "number": "1.1",
      "spec": "Verifiable Credential Rendering Methods v1.0",
      "text": "Terminology",
      "url": "https://www.w3.org/TR/vc-render-method/#terminology"
    }
  },
  "#the-nfc-render-suite": {
    "current": {
      "number": "2.2.3",
      "spec": "Verifiable Credential Rendering Methods v1.0",
      "text": "The nfc Render Suite",
      "url": "https://w3c.github.io/vc-render-method/#the-nfc-render-suite"
    },
    "snapshot": {
      "number": "2.2.3",
      "spec": "Verifiable Credential Rendering Methods v1.0",
      "text": "The nfc Render Suite",
      "url": "https://www.w3.org/TR/vc-render-method/#the-nfc-render-suite"
    }
  },
  "#the-pdf-mustache-render-suite": {
    "current": {
      "number": "2.2.2",
      "spec": "Verifiable Credential Rendering Methods v1.0",
      "text": "The pdf-mustache Render Suite",
      "url": "https://w3c.github.io/vc-render-method/#the-pdf-mustache-render-suite"
    },
    "snapshot": {
      "number": "2.2.2",
      "spec": "Verifiable Credential Rendering Methods v1.0",
      "text": "The pdf-mustache Render Suite",
      "url": "https://www.w3.org/TR/vc-render-method/#the-pdf-mustache-render-suite"
    }
  },
  "#the-rendermethod-property": {
    "current": {
      "number": "2.1",
      "spec": "Verifiable Credential Rendering Methods v1.0",
      "text": "The renderMethod Property",
      "url": "https://w3c.github.io/vc-render-method/#the-rendermethod-property"
    },
    "snapshot": {
      "number": "2.1",
      "spec": "Verifiable Credential Rendering Methods v1.0",
      "text": "The renderMethod Property",
      "url": "https://www.w3.org/TR/vc-render-method/#the-rendermethod-property"
    }
  },
  "#the-svg-mustache-render-suite": {
    "current": {
      "number": "2.2.1",
      "spec": "Verifiable Credential Rendering Methods v1.0",
      "text": "The svg-mustache Render Suite",
      "url": "https://w3c.github.io/vc-render-method/#the-svg-mustache-render-suite"
    },
    "snapshot": {
      "number": "2.2.1",
      "spec": "Verifiable Credential Rendering Methods v1.0",
      "text": "The svg-mustache Render Suite",
      "url": "https://www.w3.org/TR/vc-render-method/#the-svg-mustache-render-suite"
    }
  },
  "#title": {
    "current": {
      "number": "",
      "spec": "Verifiable Credential Rendering Methods v1.0",
      "text": "Verifiable Credential Rendering Methods v1.0",
      "url": "https://w3c.github.io/vc-render-method/#title"
    },
    "snapshot": {
      "number": "",
      "spec": "Verifiable Credential Rendering Methods v1.0",
      "text": "Verifiable Credential Rendering Methods v1.0",
      "url": "https://www.w3.org/TR/vc-render-method/#title"
    }
  },
  "#toc": {
    "current": {
      "number": "",
      "spec": "Verifiable Credential Rendering Methods v1.0",
      "text": "Table of Contents",
      "url": "https://w3c.github.io/vc-render-method/#toc"
    },
    "snapshot": {
      "number": "",
      "spec": "Verifiable Credential Rendering Methods v1.0",
      "text": "Table of Contents",
      "url": "https://www.w3.org/TR/vc-render-method/#toc"
    }
  },
  "#x1-1-terminology": {
    "current": {
      "number": "1.1",
      "spec": "Verifiable Credential Rendering Methods v1.0",
      "text": "Terminology",
      "url": "https://w3c.github.io/vc-render-method/#terminology"
    },
    "snapshot": {
      "number": "1.1",
      "spec": "Verifiable Credential Rendering Methods v1.0",
      "text": "Terminology",
      "url": "https://www.w3.org/TR/vc-render-method/#terminology"
    }
  },
  "#x1-2-conformance": {
    "current": {
      "number": "1.2",
      "spec": "Verifiable Credential Rendering Methods v1.0",
      "text": "Conformance",
      "url": "https://w3c.github.io/vc-render-method/#conformance"
    },
    "snapshot": {
      "number": "1.2",
      "spec": "Verifiable Credential Rendering Methods v1.0",
      "text": "Conformance",
      "url": "https://www.w3.org/TR/vc-render-method/#conformance"
    }
  },
  "#x1-introduction": {
    "current": {
      "number": "1",
      "spec": "Verifiable Credential Rendering Methods v1.0",
      "text": "Introduction",
      "url": "https://w3c.github.io/vc-render-method/#introduction"
    },
    "snapshot": {
      "number": "1",
      "spec": "Verifiable Credential Rendering Methods v1.0",
      "text": "Introduction",
      "url": "https://www.w3.org/TR/vc-render-method/#introduction"
    }
  },
  "#x2-1-the-rendermethod-property": {
    "current": {
      "number": "2.1",
      "spec": "Verifiable Credential Rendering Methods v1.0",
      "text": "The renderMethod Property",
      "url": "https://w3c.github.io/vc-render-method/#the-rendermethod-property"
    },
    "snapshot": {
      "number": "2.1",
      "spec": "Verifiable Credential Rendering Methods v1.0",
      "text": "The renderMethod Property",
      "url": "https://www.w3.org/TR/vc-render-method/#the-rendermethod-property"
    }
  },
  "#x2-2-1-the-svg-mustache-render-suite": {
    "current": {
      "number": "2.2.1",
      "spec": "Verifiable Credential Rendering Methods v1.0",
      "text": "The svg-mustache Render Suite",
      "url": "https://w3c.github.io/vc-render-method/#the-svg-mustache-render-suite"
    },
    "snapshot": {
      "number": "2.2.1",
      "spec": "Verifiable Credential Rendering Methods v1.0",
      "text": "The svg-mustache Render Suite",
      "url": "https://www.w3.org/TR/vc-render-method/#the-svg-mustache-render-suite"
    }
  },
  "#x2-2-2-the-pdf-mustache-render-suite": {
    "current": {
      "number": "2.2.2",
      "spec": "Verifiable Credential Rendering Methods v1.0",
      "text": "The pdf-mustache Render Suite",
      "url": "https://w3c.github.io/vc-render-method/#the-pdf-mustache-render-suite"
    },
    "snapshot": {
      "number": "2.2.2",
      "spec": "Verifiable Credential Rendering Methods v1.0",
      "text": "The pdf-mustache Render Suite",
      "url": "https://www.w3.org/TR/vc-render-method/#the-pdf-mustache-render-suite"
    }
  },
  "#x2-2-3-the-nfc-render-suite": {
    "current": {
      "number": "2.2.3",
      "spec": "Verifiable Credential Rendering Methods v1.0",
      "text": "The nfc Render Suite",
      "url": "https://w3c.github.io/vc-render-method/#the-nfc-render-suite"
    },
    "snapshot": {
      "number": "2.2.3",
      "spec": "Verifiable Credential Rendering Methods v1.0",
      "text": "The nfc Render Suite",
      "url": "https://www.w3.org/TR/vc-render-method/#the-nfc-render-suite"
    }
  },
  "#x2-2-templaterendermethod": {
    "current": {
      "number": "2.2",
      "spec": "Verifiable Credential Rendering Methods v1.0",
      "text": "TemplateRenderMethod",
      "url": "https://w3c.github.io/vc-render-method/#templaterendermethod"
    },
    "snapshot": {
      "number": "2.2",
      "spec": "Verifiable Credential Rendering Methods v1.0",
      "text": "TemplateRenderMethod",
      "url": "https://www.w3.org/TR/vc-render-method/#templaterendermethod"
    }
  },
  "#x2-3-1-1-host-to-frame-actions": {
    "current": {
      "number": "2.3.1.1",
      "spec": "Verifiable Credential Rendering Methods v1.0",
      "text": "Host-to-Frame Actions",
      "url": "https://w3c.github.io/vc-render-method/#host-to-frame-actions"
    },
    "snapshot": {
      "number": "2.3.1.1",
      "spec": "Verifiable Credential Rendering Methods v1.0",
      "text": "Host-to-Frame Actions",
      "url": "https://www.w3.org/TR/vc-render-method/#host-to-frame-actions"
    }
  },
  "#x2-3-1-2-frame-to-host-actions": {
    "current": {
      "number": "2.3.1.2",
      "spec": "Verifiable Credential Rendering Methods v1.0",
      "text": "Frame-to-Host Actions",
      "url": "https://w3c.github.io/vc-render-method/#frame-to-host-actions"
    },
    "snapshot": {
      "number": "2.3.1.2",
      "spec": "Verifiable Credential Rendering Methods v1.0",
      "text": "Frame-to-Host Actions",
      "url": "https://www.w3.org/TR/vc-render-method/#frame-to-host-actions"
    }
  },
  "#x2-3-1-action-api": {
    "current": {
      "number": "2.3.1",
      "spec": "Verifiable Credential Rendering Methods v1.0",
      "text": "Action API",
      "url": "https://w3c.github.io/vc-render-method/#action-api"
    },
    "snapshot": {
      "number": "2.3.1",
      "spec": "Verifiable Credential Rendering Methods v1.0",
      "text": "Action API",
      "url": "https://www.w3.org/TR/vc-render-method/#action-api"
    }
  },
  "#x2-3-openattestationembeddedrenderer": {
    "current": {
      "number": "2.3",
      "spec": "Verifiable Credential Rendering Methods v1.0",
      "text": "OpenAttestationEmbeddedRenderer",
      "url": "https://w3c.github.io/vc-render-method/#openattestationembeddedrenderer"
    },
    "snapshot": {
      "number": "2.3",
      "spec": "Verifiable Credential Rendering Methods v1.0",
      "text": "OpenAttestationEmbeddedRenderer",
      "url": "https://www.w3.org/TR/vc-render-method/#openattestationembeddedrenderer"
    }
  },
  "#x2-data-model": {
    "current": {
      "number": "2",
      "spec": "Verifiable Credential Rendering Methods v1.0",
      "text": "Data Model",
      "url": "https://w3c.github.io/vc-render-method/#data-model"
    },
    "snapshot": {
      "number": "2",
      "spec": "Verifiable Credential Rendering Methods v1.0",
      "text": "Data Model",
      "url": "https://www.w3.org/TR/vc-render-method/#data-model"
    }
  },
  "#x3-1-render-templaterendermethod": {
    "current": {
      "number": "3.1",
      "spec": "Verifiable Credential Rendering Methods v1.0",
      "text": "Render (TemplateRenderMethod)",
      "url": "https://w3c.github.io/vc-render-method/#render-templaterendermethod"
    },
    "snapshot": {
      "number": "3.1",
      "spec": "Verifiable Credential Rendering Methods v1.0",
      "text": "Render (TemplateRenderMethod)",
      "url": "https://www.w3.org/TR/vc-render-method/#render-templaterendermethod"
    }
  },
  "#x3-algorithms": {
    "current": {
      "number": "3",
      "spec": "Verifiable Credential Rendering Methods v1.0",
      "text": "Algorithms",
      "url": "https://w3c.github.io/vc-render-method/#algorithms"
    },
    "snapshot": {
      "number": "3",
      "spec": "Verifiable Credential Rendering Methods v1.0",
      "text": "Algorithms",
      "url": "https://www.w3.org/TR/vc-render-method/#algorithms"
    }
  },
  "#x4-security-considerations": {
    "current": {
      "number": "4",
      "spec": "Verifiable Credential Rendering Methods v1.0",
      "text": "Security Considerations",
      "url": "https://w3c.github.io/vc-render-method/#security-considerations"
    },
    "snapshot": {
      "number": "4",
      "spec": "Verifiable Credential Rendering Methods v1.0",
      "text": "Security Considerations",
      "url": "https://www.w3.org/TR/vc-render-method/#security-considerations"
    }
  },
  "#x5-privacy-considerations": {
    "current": {
      "number": "5",
      "spec": "Verifiable Credential Rendering Methods v1.0",
      "text": "Privacy Considerations",
      "url": "https://w3c.github.io/vc-render-method/#privacy-considerations"
    },
    "snapshot": {
      "number": "5",
      "spec": "Verifiable Credential Rendering Methods v1.0",
      "text": "Privacy Considerations",
      "url": "https://www.w3.org/TR/vc-render-method/#privacy-considerations"
    }
  },
  "#x6-internationalization-considerations": {
    "current": {
      "number": "6",
      "spec": "Verifiable Credential Rendering Methods v1.0",
      "text": "Internationalization Considerations",
      "url": "https://w3c.github.io/vc-render-method/#internationalization-considerations"
    },
    "snapshot": {
      "number": "6",
      "spec": "Verifiable Credential Rendering Methods v1.0",
      "text": "Internationalization Considerations",
      "url": "https://www.w3.org/TR/vc-render-method/#internationalization-considerations"
    }
  }
}